{
    "asin": "B0DSRRG4FD",
    "title": "Xiaomi Poco X7 PRO 5G + 4G LTE (for Tmobile Mint Tello & Global) (256GB + 12GB) Ai 6.67\" 50MP Gamers Phone NFC Dual sim Unlocked Model 2412DPC0AG (Black)",
    "price_history": [
        {
            "date": "2025-01-14T12:00:00",
            "price": null
        }
    ],
    "sales_rank_history": {
        "2335752011": [
            {
                "date": "2025-01-16T20:00:00",
                "sales_rank": 70445
            },
            {
                "date": "2025-01-16T22:36:00",
                "sales_rank": 75593
            },
            {
                "date": "2025-01-17T09:36:00",
                "sales_rank": 37838
            },
            {
                "date": "2025-01-17T12:52:00",
                "sales_rank": 41923
            },
            {
                "date": "2025-01-17T20:32:00",
                "sales_rank": 52108
            },
            {
                "date": "2025-01-18T08:28:00",
                "sales_rank": 80570
            },
            {
                "date": "2025-01-18T11:06:00",
                "sales_rank": 83915
            },
            {
                "date": "2025-01-18T21:52:00",
                "sales_rank": 90920
            },
            {
                "date": "2025-01-18T23:20:00",
                "sales_rank": 93563
            },
            {
                "date": "2025-01-20T03:08:00",
                "sales_rank": 123513
            },
            {
                "date": "2025-01-20T10:18:00",
                "sales_rank": 55413
            },
            {
                "date": "2025-01-20T13:12:00",
                "sales_rank": 59903
            },
            {
                "date": "2025-01-20T15:14:00",
                "sales_rank": 61697
            },
            {
                "date": "2025-01-20T19:00:00",
                "sales_rank": 66002
            },
            {
                "date": "2025-01-20T23:44:00",
                "sales_rank": 80251
            },
            {
                "date": "2025-01-21T02:52:00",
                "sales_rank": 84516
            },
            {
                "date": "2025-01-21T04:24:00",
                "sales_rank": 45301
            },
            {
                "date": "2025-01-21T07:18:00",
                "sales_rank": 53869
            },
            {
                "date": "2025-01-21T12:12:00",
                "sales_rank": 61811
            },
            {
                "date": "2025-01-21T13:44:00",
                "sales_rank": 63601
            },
            {
                "date": "2025-01-21T17:24:00",
                "sales_rank": 66040
            },
            {
                "date": "2025-01-22T01:56:00",
                "sales_rank": 36335
            },
            {
                "date": "2025-01-22T11:12:00",
                "sales_rank": 37805
            },
            {
                "date": "2025-01-22T17:48:00",
                "sales_rank": 42759
            },
            {
                "date": "2025-01-22T21:40:00",
                "sales_rank": 50464
            },
            {
                "date": "2025-01-23T00:40:00",
                "sales_rank": 54971
            },
            {
                "date": "2025-01-23T06:52:00",
                "sales_rank": 31216
            },
            {
                "date": "2025-01-23T08:52:00",
                "sales_rank": 34486
            },
            {
                "date": "2025-01-23T12:50:00",
                "sales_rank": 37723
            },
            {
                "date": "2025-01-23T15:36:00",
                "sales_rank": 38627
            },
            {
                "date": "2025-01-24T04:10:00",
                "sales_rank": 26700
            },
            {
                "date": "2025-01-24T10:56:00",
                "sales_rank": 30166
            },
            {
                "date": "2025-01-24T12:14:00",
                "sales_rank": 31578
            },
            {
                "date": "2025-01-24T21:16:00",
                "sales_rank": 28977
            },
            {
                "date": "2025-01-24T22:20:00",
                "sales_rank": 32477
            },
            {
                "date": "2025-01-25T02:12:00",
                "sales_rank": 40404
            },
            {
                "date": "2025-01-25T09:32:00",
                "sales_rank": 48597
            },
            {
                "date": "2025-01-25T18:36:00",
                "sales_rank": 55195
            },
            {
                "date": "2025-01-25T22:34:00",
                "sales_rank": 63536
            },
            {
                "date": "2025-01-26T03:28:00",
                "sales_rank": 39375
            },
            {
                "date": "2025-01-26T14:00:00",
                "sales_rank": 54429
            },
            {
                "date": "2025-01-26T19:24:00",
                "sales_rank": 56135
            },
            {
                "date": "2025-01-27T01:04:00",
                "sales_rank": 67476
            },
            {
                "date": "2025-01-27T05:00:00",
                "sales_rank": 41064
            },
            {
                "date": "2025-01-27T06:56:00",
                "sales_rank": 45815
            },
            {
                "date": "2025-01-27T19:42:00",
                "sales_rank": 27969
            },
            {
                "date": "2025-01-28T00:40:00",
                "sales_rank": 37304
            },
            {
                "date": "2025-01-28T07:16:00",
                "sales_rank": 36141
            },
            {
                "date": "2025-01-28T10:04:00",
                "sales_rank": 29191
            },
            {
                "date": "2025-01-28T11:42:00",
                "sales_rank": 30810
            },
            {
                "date": "2025-01-28T14:36:00",
                "sales_rank": 31858
            },
            {
                "date": "2025-01-28T15:56:00",
                "sales_rank": 32423
            },
            {
                "date": "2025-01-28T19:36:00",
                "sales_rank": 37087
            },
            {
                "date": "2025-01-29T08:08:00",
                "sales_rank": 42979
            },
            {
                "date": "2025-01-29T12:36:00",
                "sales_rank": 47917
            },
            {
                "date": "2025-01-29T17:00:00",
                "sales_rank": 49335
            },
            {
                "date": "2025-01-29T20:04:00",
                "sales_rank": 54473
            },
            {
                "date": "2025-01-30T05:22:00",
                "sales_rank": 40229
            },
            {
                "date": "2025-01-30T17:44:00",
                "sales_rank": 40818
            },
            {
                "date": "2025-01-31T01:36:00",
                "sales_rank": 28293
            },
            {
                "date": "2025-01-31T09:00:00",
                "sales_rank": 41460
            },
            {
                "date": "2025-01-31T13:40:00",
                "sales_rank": 34528
            },
            {
                "date": "2025-01-31T16:48:00",
                "sales_rank": 35671
            },
            {
                "date": "2025-01-31T17:24:00",
                "sales_rank": 39038
            },
            {
                "date": "2025-02-01T04:06:00",
                "sales_rank": 36368
            },
            {
                "date": "2025-02-01T17:16:00",
                "sales_rank": 48061
            },
            {
                "date": "2025-02-01T20:26:00",
                "sales_rank": 52578
            },
            {
                "date": "2025-02-01T23:34:00",
                "sales_rank": 37144
            },
            {
                "date": "2025-02-02T02:42:00",
                "sales_rank": 40831
            },
            {
                "date": "2025-02-02T06:28:00",
                "sales_rank": 48550
            },
            {
                "date": "2025-02-02T11:14:00",
                "sales_rank": 57106
            },
            {
                "date": "2025-02-02T12:54:00",
                "sales_rank": 57322
            },
            {
                "date": "2025-02-02T16:02:00",
                "sales_rank": 56993
            },
            {
                "date": "2025-02-02T17:36:00",
                "sales_rank": 57200
            },
            {
                "date": "2025-02-02T20:00:00",
                "sales_rank": 58899
            },
            {
                "date": "2025-02-02T21:44:00",
                "sales_rank": 61785
            },
            {
                "date": "2025-02-03T00:52:00",
                "sales_rank": 67813
            },
            {
                "date": "2025-02-03T07:40:00",
                "sales_rank": 44008
            },
            {
                "date": "2025-02-03T09:36:00",
                "sales_rank": 47966
            },
            {
                "date": "2025-02-03T13:32:00",
                "sales_rank": 36144
            },
            {
                "date": "2025-02-03T17:04:00",
                "sales_rank": 38847
            },
            {
                "date": "2025-02-03T22:46:00",
                "sales_rank": 48501
            },
            {
                "date": "2025-02-04T01:44:00",
                "sales_rank": 52905
            },
            {
                "date": "2025-02-04T02:06:00",
                "sales_rank": 56403
            },
            {
                "date": "2025-02-04T04:40:00",
                "sales_rank": 60248
            },
            {
                "date": "2025-02-04T09:08:00",
                "sales_rank": 39136
            },
            {
                "date": "2025-02-04T15:48:00",
                "sales_rank": 40617
            },
            {
                "date": "2025-02-04T19:28:00",
                "sales_rank": 46500
            },
            {
                "date": "2025-02-05T00:52:00",
                "sales_rank": 35242
            },
            {
                "date": "2025-02-05T06:04:00",
                "sales_rank": 44229
            },
            {
                "date": "2025-02-05T09:20:00",
                "sales_rank": 48496
            },
            {
                "date": "2025-02-05T13:08:00",
                "sales_rank": 54032
            },
            {
                "date": "2025-02-05T14:16:00",
                "sales_rank": 54475
            },
            {
                "date": "2025-02-05T16:04:00",
                "sales_rank": 54683
            },
            {
                "date": "2025-02-05T21:48:00",
                "sales_rank": 61378
            },
            {
                "date": "2025-02-06T00:56:00",
                "sales_rank": 66285
            },
            {
                "date": "2025-02-06T04:32:00",
                "sales_rank": 44203
            },
            {
                "date": "2025-02-06T16:32:00",
                "sales_rank": 58890
            },
            {
                "date": "2025-02-07T00:28:00",
                "sales_rank": 52896
            },
            {
                "date": "2025-02-07T04:58:00",
                "sales_rank": 66067
            },
            {
                "date": "2025-02-07T09:32:00",
                "sales_rank": 25986
            },
            {
                "date": "2025-02-07T11:20:00",
                "sales_rank": 22660
            },
            {
                "date": "2025-02-07T13:38:00",
                "sales_rank": 23851
            },
            {
                "date": "2025-02-07T16:40:00",
                "sales_rank": 26672
            },
            {
                "date": "2025-02-07T21:12:00",
                "sales_rank": 20650
            },
            {
                "date": "2025-02-08T01:20:00",
                "sales_rank": 26763
            },
            {
                "date": "2025-02-08T13:44:00",
                "sales_rank": 26219
            },
            {
                "date": "2025-02-08T14:24:00",
                "sales_rank": 27011
            },
            {
                "date": "2025-02-08T18:24:00",
                "sales_rank": 17893
            },
            {
                "date": "2025-02-08T23:10:00",
                "sales_rank": 19207
            },
            {
                "date": "2025-02-09T10:32:00",
                "sales_rank": 23060
            },
            {
                "date": "2025-02-09T13:52:00",
                "sales_rank": 24852
            },
            {
                "date": "2025-02-09T18:48:00",
                "sales_rank": 26235
            },
            {
                "date": "2025-02-10T00:06:00",
                "sales_rank": 34914
            },
            {
                "date": "2025-02-10T02:48:00",
                "sales_rank": 37653
            },
            {
                "date": "2025-02-10T07:44:00",
                "sales_rank": 45588
            },
            {
                "date": "2025-02-10T10:52:00",
                "sales_rank": 47106
            },
            {
                "date": "2025-02-10T14:00:00",
                "sales_rank": 31946
            },
            {
                "date": "2025-02-10T21:24:00",
                "sales_rank": 35509
            },
            {
                "date": "2025-02-10T22:36:00",
                "sales_rank": 38911
            },
            {
                "date": "2025-02-11T02:08:00",
                "sales_rank": 45841
            },
            {
                "date": "2025-02-11T05:40:00",
                "sales_rank": 52230
            },
            {
                "date": "2025-02-11T11:12:00",
                "sales_rank": 40493
            },
            {
                "date": "2025-02-11T14:20:00",
                "sales_rank": 41013
            },
            {
                "date": "2025-02-11T18:20:00",
                "sales_rank": 42598
            },
            {
                "date": "2025-02-11T21:52:00",
                "sales_rank": 49867
            },
            {
                "date": "2025-02-12T00:04:00",
                "sales_rank": 53332
            },
            {
                "date": "2025-02-12T04:24:00",
                "sales_rank": 59229
            },
            {
                "date": "2025-02-12T07:24:00",
                "sales_rank": 36851
            },
            {
                "date": "2025-02-12T10:38:00",
                "sales_rank": 24888
            },
            {
                "date": "2025-02-12T14:44:00",
                "sales_rank": 21949
            },
            {
                "date": "2025-02-12T16:22:00",
                "sales_rank": 23145
            },
            {
                "date": "2025-02-12T19:10:00",
                "sales_rank": 25126
            },
            {
                "date": "2025-02-12T22:36:00",
                "sales_rank": 31532
            },
            {
                "date": "2025-02-13T02:58:00",
                "sales_rank": 28520
            },
            {
                "date": "2025-02-13T04:30:00",
                "sales_rank": 25503
            },
            {
                "date": "2025-02-13T07:08:00",
                "sales_rank": 28349
            },
            {
                "date": "2025-02-13T09:56:00",
                "sales_rank": 25730
            },
            {
                "date": "2025-02-13T13:30:00",
                "sales_rank": 26728
            },
            {
                "date": "2025-02-13T17:58:00",
                "sales_rank": 30255
            },
            {
                "date": "2025-02-13T22:20:00",
                "sales_rank": 34589
            },
            {
                "date": "2025-02-14T02:50:00",
                "sales_rank": 41361
            },
            {
                "date": "2025-02-14T04:24:00",
                "sales_rank": 29823
            },
            {
                "date": "2025-02-14T07:52:00",
                "sales_rank": 35638
            },
            {
                "date": "2025-02-14T10:20:00",
                "sales_rank": 37778
            },
            {
                "date": "2025-02-14T12:22:00",
                "sales_rank": 28020
            },
            {
                "date": "2025-02-14T14:02:00",
                "sales_rank": 28873
            },
            {
                "date": "2025-02-14T16:58:00",
                "sales_rank": 29762
            },
            {
                "date": "2025-02-14T19:08:00",
                "sales_rank": 31307
            },
            {
                "date": "2025-02-15T04:26:00",
                "sales_rank": 34618
            },
            {
                "date": "2025-02-15T06:40:00",
                "sales_rank": 38437
            },
            {
                "date": "2025-02-15T09:48:00",
                "sales_rank": 42897
            },
            {
                "date": "2025-02-15T14:58:00",
                "sales_rank": 44065
            },
            {
                "date": "2025-02-15T20:58:00",
                "sales_rank": 51295
            },
            {
                "date": "2025-02-16T01:46:00",
                "sales_rank": 35151
            },
            {
                "date": "2025-02-16T02:52:00",
                "sales_rank": 40218
            },
            {
                "date": "2025-02-16T06:16:00",
                "sales_rank": 46621
            },
            {
                "date": "2025-02-16T10:24:00",
                "sales_rank": 51497
            },
            {
                "date": "2025-02-16T13:16:00",
                "sales_rank": 52353
            },
            {
                "date": "2025-02-16T16:28:00",
                "sales_rank": 52034
            },
            {
                "date": "2025-02-16T20:48:00",
                "sales_rank": 54871
            },
            {
                "date": "2025-02-17T04:12:00",
                "sales_rank": 73654
            },
            {
                "date": "2025-02-17T06:22:00",
                "sales_rank": 39946
            },
            {
                "date": "2025-02-17T08:32:00",
                "sales_rank": 43561
            },
            {
                "date": "2025-02-17T09:30:00",
                "sales_rank": 46085
            },
            {
                "date": "2025-02-17T13:20:00",
                "sales_rank": 48882
            },
            {
                "date": "2025-02-17T17:28:00",
                "sales_rank": 50602
            },
            {
                "date": "2025-02-17T23:06:00",
                "sales_rank": 62193
            },
            {
                "date": "2025-02-18T02:36:00",
                "sales_rank": 67176
            },
            {
                "date": "2025-02-18T09:00:00",
                "sales_rank": 30250
            },
            {
                "date": "2025-02-18T11:58:00",
                "sales_rank": 22809
            },
            {
                "date": "2025-02-18T23:24:00",
                "sales_rank": 24429
            },
            {
                "date": "2025-02-19T10:00:00",
                "sales_rank": 32122
            },
            {
                "date": "2025-02-19T12:24:00",
                "sales_rank": 34563
            },
            {
                "date": "2025-02-19T16:04:00",
                "sales_rank": 34994
            },
            {
                "date": "2025-02-19T19:18:00",
                "sales_rank": 37371
            },
            {
                "date": "2025-02-19T21:28:00",
                "sales_rank": 40025
            },
            {
                "date": "2025-02-20T02:18:00",
                "sales_rank": 50877
            },
            {
                "date": "2025-02-20T10:36:00",
                "sales_rank": 27340
            },
            {
                "date": "2025-02-20T17:24:00",
                "sales_rank": 24124
            },
            {
                "date": "2025-02-20T23:16:00",
                "sales_rank": 33368
            },
            {
                "date": "2025-02-21T06:16:00",
                "sales_rank": 45660
            },
            {
                "date": "2025-02-21T08:04:00",
                "sales_rank": 32338
            },
            {
                "date": "2025-02-21T10:28:00",
                "sales_rank": 34110
            },
            {
                "date": "2025-02-21T18:54:00",
                "sales_rank": 39424
            },
            {
                "date": "2025-02-22T00:04:00",
                "sales_rank": 44504
            },
            {
                "date": "2025-02-22T05:36:00",
                "sales_rank": 33027
            },
            {
                "date": "2025-02-22T09:48:00",
                "sales_rank": 23940
            },
            {
                "date": "2025-02-22T13:38:00",
                "sales_rank": 26195
            },
            {
                "date": "2025-02-22T16:02:00",
                "sales_rank": 27149
            },
            {
                "date": "2025-02-22T19:02:00",
                "sales_rank": 28931
            },
            {
                "date": "2025-02-22T20:20:00",
                "sales_rank": 31945
            },
            {
                "date": "2025-02-22T23:02:00",
                "sales_rank": 26457
            },
            {
                "date": "2025-02-23T00:04:00",
                "sales_rank": 23365
            },
            {
                "date": "2025-02-23T02:32:00",
                "sales_rank": 26544
            },
            {
                "date": "2025-02-23T05:42:00",
                "sales_rank": 25886
            },
            {
                "date": "2025-02-23T09:04:00",
                "sales_rank": 28990
            },
            {
                "date": "2025-02-23T14:34:00",
                "sales_rank": 31495
            },
            {
                "date": "2025-02-23T18:36:00",
                "sales_rank": 33883
            },
            {
                "date": "2025-02-23T23:00:00",
                "sales_rank": 23127
            },
            {
                "date": "2025-02-24T00:12:00",
                "sales_rank": 26396
            },
            {
                "date": "2025-02-24T05:12:00",
                "sales_rank": 20462
            },
            {
                "date": "2025-02-24T12:56:00",
                "sales_rank": 18680
            },
            {
                "date": "2025-02-24T17:36:00",
                "sales_rank": 19861
            },
            {
                "date": "2025-02-24T20:28:00",
                "sales_rank": 22258
            },
            {
                "date": "2025-02-24T23:48:00",
                "sales_rank": 27336
            },
            {
                "date": "2025-02-25T01:20:00",
                "sales_rank": 28549
            },
            {
                "date": "2025-02-25T03:02:00",
                "sales_rank": 24692
            },
            {
                "date": "2025-02-25T05:44:00",
                "sales_rank": 27254
            },
            {
                "date": "2025-02-25T09:08:00",
                "sales_rank": 32221
            },
            {
                "date": "2025-02-25T13:16:00",
                "sales_rank": 33619
            },
            {
                "date": "2025-02-25T15:26:00",
                "sales_rank": 33546
            },
            {
                "date": "2025-02-25T18:36:00",
                "sales_rank": 35759
            },
            {
                "date": "2025-02-25T23:34:00",
                "sales_rank": 40288
            },
            {
                "date": "2025-02-26T05:44:00",
                "sales_rank": 37086
            },
            {
                "date": "2025-02-26T08:46:00",
                "sales_rank": 20025
            },
            {
                "date": "2025-02-26T12:52:00",
                "sales_rank": 23496
            },
            {
                "date": "2025-02-26T21:28:00",
                "sales_rank": 19200
            },
            {
                "date": "2025-02-27T00:36:00",
                "sales_rank": 25352
            },
            {
                "date": "2025-02-27T03:20:00",
                "sales_rank": 26762
            },
            {
                "date": "2025-02-27T07:28:00",
                "sales_rank": 34016
            },
            {
                "date": "2025-02-27T10:08:00",
                "sales_rank": 38893
            },
            {
                "date": "2025-02-27T15:08:00",
                "sales_rank": 27622
            },
            {
                "date": "2025-02-27T18:16:00",
                "sales_rank": 29174
            },
            {
                "date": "2025-02-27T19:20:00",
                "sales_rank": 31531
            },
            {
                "date": "2025-02-27T23:00:00",
                "sales_rank": 26212
            },
            {
                "date": "2025-02-28T02:24:00",
                "sales_rank": 24872
            },
            {
                "date": "2025-02-28T02:32:00",
                "sales_rank": 27538
            },
            {
                "date": "2025-02-28T07:16:00",
                "sales_rank": 34073
            },
            {
                "date": "2025-02-28T12:24:00",
                "sales_rank": 37445
            },
            {
                "date": "2025-02-28T22:02:00",
                "sales_rank": 34549
            },
            {
                "date": "2025-03-01T01:10:00",
                "sales_rank": 38510
            },
            {
                "date": "2025-03-01T04:18:00",
                "sales_rank": 39874
            },
            {
                "date": "2025-03-01T05:26:00",
                "sales_rank": 45302
            },
            {
                "date": "2025-03-01T08:34:00",
                "sales_rank": 50338
            },
            {
                "date": "2025-03-01T12:12:00",
                "sales_rank": 51837
            },
            {
                "date": "2025-03-01T16:12:00",
                "sales_rank": 51012
            },
            {
                "date": "2025-03-01T19:24:00",
                "sales_rank": 52215
            },
            {
                "date": "2025-03-02T08:24:00",
                "sales_rank": 75846
            },
            {
                "date": "2025-03-02T11:54:00",
                "sales_rank": 76119
            },
            {
                "date": "2025-03-02T16:04:00",
                "sales_rank": 72417
            },
            {
                "date": "2025-03-03T00:20:00",
                "sales_rank": 43531
            },
            {
                "date": "2025-03-03T02:26:00",
                "sales_rank": 34153
            },
            {
                "date": "2025-03-03T07:36:00",
                "sales_rank": 40466
            },
            {
                "date": "2025-03-03T11:44:00",
                "sales_rank": 48853
            },
            {
                "date": "2025-03-04T00:06:00",
                "sales_rank": 46608
            },
            {
                "date": "2025-03-04T04:16:00",
                "sales_rank": 54918
            },
            {
                "date": "2025-03-04T09:18:00",
                "sales_rank": 40474
            },
            {
                "date": "2025-03-04T12:14:00",
                "sales_rank": 45426
            },
            {
                "date": "2025-03-04T16:04:00",
                "sales_rank": 46422
            },
            {
                "date": "2025-03-04T20:48:00",
                "sales_rank": 51280
            },
            {
                "date": "2025-03-05T02:02:00",
                "sales_rank": 36469
            },
            {
                "date": "2025-03-05T04:20:00",
                "sales_rank": 40055
            },
            {
                "date": "2025-03-05T07:28:00",
                "sales_rank": 35906
            },
            {
                "date": "2025-03-05T13:20:00",
                "sales_rank": 41926
            },
            {
                "date": "2025-03-05T22:36:00",
                "sales_rank": 53983
            },
            {
                "date": "2025-03-06T14:14:00",
                "sales_rank": 49249
            },
            {
                "date": "2025-03-06T17:08:00",
                "sales_rank": 50529
            },
            {
                "date": "2025-03-07T01:26:00",
                "sales_rank": 63702
            },
            {
                "date": "2025-03-07T08:44:00",
                "sales_rank": 47504
            },
            {
                "date": "2025-03-07T14:56:00",
                "sales_rank": 52398
            },
            {
                "date": "2025-03-07T21:04:00",
                "sales_rank": 58746
            },
            {
                "date": "2025-03-08T06:58:00",
                "sales_rank": 63473
            },
            {
                "date": "2025-03-08T14:12:00",
                "sales_rank": 63043
            },
            {
                "date": "2025-03-08T18:00:00",
                "sales_rank": 61186
            },
            {
                "date": "2025-03-08T19:40:00",
                "sales_rank": 62050
            },
            {
                "date": "2025-03-08T20:44:00",
                "sales_rank": 64652
            },
            {
                "date": "2025-03-09T00:36:00",
                "sales_rank": 72991
            },
            {
                "date": "2025-03-09T23:22:00",
                "sales_rank": 82687
            },
            {
                "date": "2025-03-10T01:48:00",
                "sales_rank": 85285
            },
            {
                "date": "2025-03-10T08:22:00",
                "sales_rank": 92567
            },
            {
                "date": "2025-03-10T12:08:00",
                "sales_rank": 94679
            },
            {
                "date": "2025-03-10T13:56:00",
                "sales_rank": 93810
            },
            {
                "date": "2025-03-10T18:22:00",
                "sales_rank": 92107
            },
            {
                "date": "2025-03-10T21:56:00",
                "sales_rank": 93527
            },
            {
                "date": "2025-03-11T00:12:00",
                "sales_rank": 44293
            },
            {
                "date": "2025-03-11T04:32:00",
                "sales_rank": 34013
            },
            {
                "date": "2025-03-11T10:50:00",
                "sales_rank": 46991
            },
            {
                "date": "2025-03-11T13:58:00",
                "sales_rank": 48210
            },
            {
                "date": "2025-03-11T18:00:00",
                "sales_rank": 51363
            },
            {
                "date": "2025-03-11T18:24:00",
                "sales_rank": 54369
            },
            {
                "date": "2025-03-11T21:40:00",
                "sales_rank": 58020
            },
            {
                "date": "2025-03-12T02:14:00",
                "sales_rank": 68696
            },
            {
                "date": "2025-03-12T08:26:00",
                "sales_rank": 79099
            },
            {
                "date": "2025-03-12T17:44:00",
                "sales_rank": 50684
            },
            {
                "date": "2025-03-12T23:08:00",
                "sales_rank": 60262
            },
            {
                "date": "2025-03-13T05:58:00",
                "sales_rank": 71785
            },
            {
                "date": "2025-03-13T09:06:00",
                "sales_rank": 78383
            },
            {
                "date": "2025-03-13T12:14:00",
                "sales_rank": 79599
            },
            {
                "date": "2025-03-13T14:20:00",
                "sales_rank": 78928
            },
            {
                "date": "2025-03-13T18:46:00",
                "sales_rank": 37774
            },
            {
                "date": "2025-03-14T01:52:00",
                "sales_rank": 56646
            },
            {
                "date": "2025-03-14T11:06:00",
                "sales_rank": 32486
            },
            {
                "date": "2025-03-14T14:14:00",
                "sales_rank": 35239
            },
            {
                "date": "2025-03-14T18:40:00",
                "sales_rank": 41059
            },
            {
                "date": "2025-03-14T23:34:00",
                "sales_rank": 48171
            },
            {
                "date": "2025-03-15T08:52:00",
                "sales_rank": 67537
            },
            {
                "date": "2025-03-15T20:58:00",
                "sales_rank": 72538
            },
            {
                "date": "2025-03-16T02:50:00",
                "sales_rank": 37423
            },
            {
                "date": "2025-03-16T05:58:00",
                "sales_rank": 42947
            },
            {
                "date": "2025-03-16T09:20:00",
                "sales_rank": 48335
            },
            {
                "date": "2025-03-16T14:32:00",
                "sales_rank": 49578
            },
            {
                "date": "2025-03-16T19:38:00",
                "sales_rank": 54851
            },
            {
                "date": "2025-03-16T23:48:00",
                "sales_rank": 65626
            },
            {
                "date": "2025-03-17T04:28:00",
                "sales_rank": 76890
            },
            {
                "date": "2025-03-17T07:36:00",
                "sales_rank": 79807
            },
            {
                "date": "2025-03-17T11:12:00",
                "sales_rank": 81541
            },
            {
                "date": "2025-03-17T18:12:00",
                "sales_rank": 78713
            },
            {
                "date": "2025-03-17T21:54:00",
                "sales_rank": 79677
            },
            {
                "date": "2025-03-18T01:02:00",
                "sales_rank": 30507
            },
            {
                "date": "2025-03-18T03:46:00",
                "sales_rank": 34498
            },
            {
                "date": "2025-03-18T05:58:00",
                "sales_rank": 31369
            },
            {
                "date": "2025-03-18T09:16:00",
                "sales_rank": 36680
            },
            {
                "date": "2025-03-18T12:40:00",
                "sales_rank": 37825
            },
            {
                "date": "2025-03-18T16:40:00",
                "sales_rank": 39732
            },
            {
                "date": "2025-03-18T18:00:00",
                "sales_rank": 43008
            }
        ],
        "7072561011": [
            {
                "date": "2025-01-16T20:00:00",
                "sales_rank": 1269
            },
            {
                "date": "2025-01-16T22:36:00",
                "sales_rank": 1370
            },
            {
                "date": "2025-01-17T09:36:00",
                "sales_rank": 694
            },
            {
                "date": "2025-01-17T12:52:00",
                "sales_rank": 771
            },
            {
                "date": "2025-01-17T20:32:00",
                "sales_rank": 952
            },
            {
                "date": "2025-01-18T08:28:00",
                "sales_rank": 1428
            },
            {
                "date": "2025-01-18T11:06:00",
                "sales_rank": 1466
            },
            {
                "date": "2025-01-18T21:52:00",
                "sales_rank": 1610
            },
            {
                "date": "2025-01-18T23:20:00",
                "sales_rank": 1664
            },
            {
                "date": "2025-01-20T03:08:00",
                "sales_rank": 2123
            },
            {
                "date": "2025-01-20T10:18:00",
                "sales_rank": 961
            },
            {
                "date": "2025-01-20T13:12:00",
                "sales_rank": 1028
            },
            {
                "date": "2025-01-20T15:14:00",
                "sales_rank": 1051
            },
            {
                "date": "2025-01-20T19:00:00",
                "sales_rank": 1111
            },
            {
                "date": "2025-01-20T23:44:00",
                "sales_rank": 1392
            },
            {
                "date": "2025-01-21T02:52:00",
                "sales_rank": 1467
            },
            {
                "date": "2025-01-21T04:24:00",
                "sales_rank": 801
            },
            {
                "date": "2025-01-21T07:18:00",
                "sales_rank": 943
            },
            {
                "date": "2025-01-21T12:12:00",
                "sales_rank": 1070
            },
            {
                "date": "2025-01-21T13:44:00",
                "sales_rank": 1108
            },
            {
                "date": "2025-01-21T17:24:00",
                "sales_rank": 1142
            },
            {
                "date": "2025-01-22T01:56:00",
                "sales_rank": 655
            },
            {
                "date": "2025-01-22T11:12:00",
                "sales_rank": 695
            },
            {
                "date": "2025-01-22T17:48:00",
                "sales_rank": 790
            },
            {
                "date": "2025-01-22T21:40:00",
                "sales_rank": 928
            },
            {
                "date": "2025-01-23T00:40:00",
                "sales_rank": 1023
            },
            {
                "date": "2025-01-23T06:52:00",
                "sales_rank": 571
            },
            {
                "date": "2025-01-23T08:52:00",
                "sales_rank": 627
            },
            {
                "date": "2025-01-23T12:50:00",
                "sales_rank": 676
            },
            {
                "date": "2025-01-23T15:36:00",
                "sales_rank": 695
            },
            {
                "date": "2025-01-24T04:10:00",
                "sales_rank": 476
            },
            {
                "date": "2025-01-24T10:56:00",
                "sales_rank": 551
            },
            {
                "date": "2025-01-24T12:14:00",
                "sales_rank": 582
            },
            {
                "date": "2025-01-24T21:16:00",
                "sales_rank": 527
            },
            {
                "date": "2025-01-24T22:20:00",
                "sales_rank": 593
            },
            {
                "date": "2025-01-25T02:12:00",
                "sales_rank": 736
            },
            {
                "date": "2025-01-25T09:32:00",
                "sales_rank": 897
            },
            {
                "date": "2025-01-25T18:36:00",
                "sales_rank": 1008
            },
            {
                "date": "2025-01-25T22:34:00",
                "sales_rank": 1151
            },
            {
                "date": "2025-01-26T03:28:00",
                "sales_rank": 724
            },
            {
                "date": "2025-01-26T14:00:00",
                "sales_rank": 980
            },
            {
                "date": "2025-01-26T19:24:00",
                "sales_rank": 1006
            },
            {
                "date": "2025-01-27T01:04:00",
                "sales_rank": 1181
            },
            {
                "date": "2025-01-27T05:00:00",
                "sales_rank": 740
            },
            {
                "date": "2025-01-27T06:56:00",
                "sales_rank": 824
            },
            {
                "date": "2025-01-27T19:42:00",
                "sales_rank": 480
            },
            {
                "date": "2025-01-28T00:40:00",
                "sales_rank": 661
            },
            {
                "date": "2025-01-28T07:16:00",
                "sales_rank": 663
            },
            {
                "date": "2025-01-28T10:04:00",
                "sales_rank": 516
            },
            {
                "date": "2025-01-28T11:42:00",
                "sales_rank": 547
            },
            {
                "date": "2025-01-28T14:36:00",
                "sales_rank": 570
            },
            {
                "date": "2025-01-28T15:56:00",
                "sales_rank": 588
            },
            {
                "date": "2025-01-28T19:36:00",
                "sales_rank": 665
            },
            {
                "date": "2025-01-29T08:08:00",
                "sales_rank": 828
            },
            {
                "date": "2025-01-29T12:36:00",
                "sales_rank": 918
            },
            {
                "date": "2025-01-29T17:00:00",
                "sales_rank": 949
            },
            {
                "date": "2025-01-29T20:04:00",
                "sales_rank": 1027
            },
            {
                "date": "2025-01-30T05:22:00",
                "sales_rank": 762
            },
            {
                "date": "2025-01-30T17:44:00",
                "sales_rank": 750
            },
            {
                "date": "2025-01-31T01:36:00",
                "sales_rank": 517
            },
            {
                "date": "2025-01-31T09:00:00",
                "sales_rank": 765
            },
            {
                "date": "2025-01-31T13:40:00",
                "sales_rank": 630
            },
            {
                "date": "2025-01-31T16:48:00",
                "sales_rank": 657
            },
            {
                "date": "2025-01-31T17:24:00",
                "sales_rank": 712
            },
            {
                "date": "2025-02-01T04:06:00",
                "sales_rank": 666
            },
            {
                "date": "2025-02-01T17:16:00",
                "sales_rank": 889
            },
            {
                "date": "2025-02-01T20:26:00",
                "sales_rank": 965
            },
            {
                "date": "2025-02-01T23:34:00",
                "sales_rank": 670
            },
            {
                "date": "2025-02-02T02:42:00",
                "sales_rank": 725
            },
            {
                "date": "2025-02-02T06:28:00",
                "sales_rank": 871
            },
            {
                "date": "2025-02-02T11:14:00",
                "sales_rank": 1014
            },
            {
                "date": "2025-02-02T12:54:00",
                "sales_rank": 1030
            },
            {
                "date": "2025-02-02T16:02:00",
                "sales_rank": 1029
            },
            {
                "date": "2025-02-02T20:00:00",
                "sales_rank": 1047
            },
            {
                "date": "2025-02-02T21:44:00",
                "sales_rank": 1087
            },
            {
                "date": "2025-02-03T00:52:00",
                "sales_rank": 1181
            },
            {
                "date": "2025-02-03T07:40:00",
                "sales_rank": 770
            },
            {
                "date": "2025-02-03T09:36:00",
                "sales_rank": 847
            },
            {
                "date": "2025-02-03T13:32:00",
                "sales_rank": 621
            },
            {
                "date": "2025-02-03T17:04:00",
                "sales_rank": 676
            },
            {
                "date": "2025-02-03T22:46:00",
                "sales_rank": 867
            },
            {
                "date": "2025-02-04T01:44:00",
                "sales_rank": 971
            },
            {
                "date": "2025-02-04T02:06:00",
                "sales_rank": 1027
            },
            {
                "date": "2025-02-04T04:40:00",
                "sales_rank": 1108
            },
            {
                "date": "2025-02-04T09:08:00",
                "sales_rank": 723
            },
            {
                "date": "2025-02-04T15:48:00",
                "sales_rank": 740
            },
            {
                "date": "2025-02-04T19:28:00",
                "sales_rank": 853
            },
            {
                "date": "2025-02-05T00:52:00",
                "sales_rank": 648
            },
            {
                "date": "2025-02-05T06:04:00",
                "sales_rank": 825
            },
            {
                "date": "2025-02-05T09:20:00",
                "sales_rank": 884
            },
            {
                "date": "2025-02-05T13:08:00",
                "sales_rank": 991
            },
            {
                "date": "2025-02-05T14:16:00",
                "sales_rank": 995
            },
            {
                "date": "2025-02-05T21:48:00",
                "sales_rank": 1138
            },
            {
                "date": "2025-02-06T00:56:00",
                "sales_rank": 1218
            },
            {
                "date": "2025-02-06T04:32:00",
                "sales_rank": 824
            },
            {
                "date": "2025-02-06T16:32:00",
                "sales_rank": 1105
            },
            {
                "date": "2025-02-07T00:28:00",
                "sales_rank": 981
            },
            {
                "date": "2025-02-07T04:58:00",
                "sales_rank": 1221
            },
            {
                "date": "2025-02-07T09:32:00",
                "sales_rank": 456
            },
            {
                "date": "2025-02-07T11:20:00",
                "sales_rank": 391
            },
            {
                "date": "2025-02-07T13:38:00",
                "sales_rank": 410
            },
            {
                "date": "2025-02-07T16:40:00",
                "sales_rank": 465
            },
            {
                "date": "2025-02-07T21:12:00",
                "sales_rank": 368
            },
            {
                "date": "2025-02-08T01:20:00",
                "sales_rank": 494
            },
            {
                "date": "2025-02-08T13:44:00",
                "sales_rank": 471
            },
            {
                "date": "2025-02-08T14:24:00",
                "sales_rank": 491
            },
            {
                "date": "2025-02-08T18:24:00",
                "sales_rank": 313
            },
            {
                "date": "2025-02-08T23:10:00",
                "sales_rank": 325
            },
            {
                "date": "2025-02-09T10:32:00",
                "sales_rank": 394
            },
            {
                "date": "2025-02-09T13:52:00",
                "sales_rank": 421
            },
            {
                "date": "2025-02-09T18:48:00",
                "sales_rank": 439
            },
            {
                "date": "2025-02-10T00:06:00",
                "sales_rank": 610
            },
            {
                "date": "2025-02-10T02:48:00",
                "sales_rank": 667
            },
            {
                "date": "2025-02-10T07:44:00",
                "sales_rank": 788
            },
            {
                "date": "2025-02-10T10:52:00",
                "sales_rank": 809
            },
            {
                "date": "2025-02-10T14:00:00",
                "sales_rank": 559
            },
            {
                "date": "2025-02-10T21:24:00",
                "sales_rank": 630
            },
            {
                "date": "2025-02-10T22:36:00",
                "sales_rank": 689
            },
            {
                "date": "2025-02-11T02:08:00",
                "sales_rank": 851
            },
            {
                "date": "2025-02-11T05:40:00",
                "sales_rank": 976
            },
            {
                "date": "2025-02-11T11:12:00",
                "sales_rank": 753
            },
            {
                "date": "2025-02-11T14:20:00",
                "sales_rank": 765
            },
            {
                "date": "2025-02-11T18:20:00",
                "sales_rank": 800
            },
            {
                "date": "2025-02-11T21:52:00",
                "sales_rank": 931
            },
            {
                "date": "2025-02-12T00:04:00",
                "sales_rank": 995
            },
            {
                "date": "2025-02-12T04:24:00",
                "sales_rank": 1116
            },
            {
                "date": "2025-02-12T07:24:00",
                "sales_rank": 696
            },
            {
                "date": "2025-02-12T10:38:00",
                "sales_rank": 439
            },
            {
                "date": "2025-02-12T14:44:00",
                "sales_rank": 383
            },
            {
                "date": "2025-02-12T16:22:00",
                "sales_rank": 409
            },
            {
                "date": "2025-02-12T19:10:00",
                "sales_rank": 434
            },
            {
                "date": "2025-02-12T22:36:00",
                "sales_rank": 566
            },
            {
                "date": "2025-02-13T02:58:00",
                "sales_rank": 522
            },
            {
                "date": "2025-02-13T04:30:00",
                "sales_rank": 453
            },
            {
                "date": "2025-02-13T07:08:00",
                "sales_rank": 502
            },
            {
                "date": "2025-02-13T09:56:00",
                "sales_rank": 446
            },
            {
                "date": "2025-02-13T13:30:00",
                "sales_rank": 464
            },
            {
                "date": "2025-02-13T17:58:00",
                "sales_rank": 546
            },
            {
                "date": "2025-02-13T22:20:00",
                "sales_rank": 634
            },
            {
                "date": "2025-02-14T02:50:00",
                "sales_rank": 754
            },
            {
                "date": "2025-02-14T04:24:00",
                "sales_rank": 539
            },
            {
                "date": "2025-02-14T07:52:00",
                "sales_rank": 640
            },
            {
                "date": "2025-02-14T10:20:00",
                "sales_rank": 672
            },
            {
                "date": "2025-02-14T12:22:00",
                "sales_rank": 498
            },
            {
                "date": "2025-02-14T14:02:00",
                "sales_rank": 513
            },
            {
                "date": "2025-02-14T16:58:00",
                "sales_rank": 527
            },
            {
                "date": "2025-02-14T19:08:00",
                "sales_rank": 556
            },
            {
                "date": "2025-02-15T04:26:00",
                "sales_rank": 641
            },
            {
                "date": "2025-02-15T06:40:00",
                "sales_rank": 718
            },
            {
                "date": "2025-02-15T09:48:00",
                "sales_rank": 804
            },
            {
                "date": "2025-02-15T14:58:00",
                "sales_rank": 825
            },
            {
                "date": "2025-02-15T20:58:00",
                "sales_rank": 951
            },
            {
                "date": "2025-02-16T01:46:00",
                "sales_rank": 633
            },
            {
                "date": "2025-02-16T02:52:00",
                "sales_rank": 727
            },
            {
                "date": "2025-02-16T06:16:00",
                "sales_rank": 815
            },
            {
                "date": "2025-02-16T10:24:00",
                "sales_rank": 918
            },
            {
                "date": "2025-02-16T13:16:00",
                "sales_rank": 933
            },
            {
                "date": "2025-02-16T20:48:00",
                "sales_rank": 994
            },
            {
                "date": "2025-02-17T04:12:00",
                "sales_rank": 1312
            },
            {
                "date": "2025-02-17T06:22:00",
                "sales_rank": 674
            },
            {
                "date": "2025-02-17T08:32:00",
                "sales_rank": 723
            },
            {
                "date": "2025-02-17T09:30:00",
                "sales_rank": 781
            },
            {
                "date": "2025-02-17T13:20:00",
                "sales_rank": 830
            },
            {
                "date": "2025-02-17T17:28:00",
                "sales_rank": 865
            },
            {
                "date": "2025-02-17T23:06:00",
                "sales_rank": 1118
            },
            {
                "date": "2025-02-18T02:36:00",
                "sales_rank": 1221
            },
            {
                "date": "2025-02-18T09:00:00",
                "sales_rank": 509
            },
            {
                "date": "2025-02-18T11:58:00",
                "sales_rank": 362
            },
            {
                "date": "2025-02-18T23:24:00",
                "sales_rank": 404
            },
            {
                "date": "2025-02-19T10:00:00",
                "sales_rank": 551
            },
            {
                "date": "2025-02-19T12:24:00",
                "sales_rank": 597
            },
            {
                "date": "2025-02-19T16:04:00",
                "sales_rank": 610
            },
            {
                "date": "2025-02-19T19:18:00",
                "sales_rank": 654
            },
            {
                "date": "2025-02-19T21:28:00",
                "sales_rank": 723
            },
            {
                "date": "2025-02-20T02:18:00",
                "sales_rank": 967
            },
            {
                "date": "2025-02-20T10:36:00",
                "sales_rank": 471
            },
            {
                "date": "2025-02-20T17:24:00",
                "sales_rank": 422
            },
            {
                "date": "2025-02-20T23:16:00",
                "sales_rank": 606
            },
            {
                "date": "2025-02-21T06:16:00",
                "sales_rank": 834
            },
            {
                "date": "2025-02-21T08:04:00",
                "sales_rank": 595
            },
            {
                "date": "2025-02-21T10:28:00",
                "sales_rank": 623
            },
            {
                "date": "2025-02-21T18:54:00",
                "sales_rank": 737
            },
            {
                "date": "2025-02-22T00:04:00",
                "sales_rank": 844
            },
            {
                "date": "2025-02-22T05:36:00",
                "sales_rank": 604
            },
            {
                "date": "2025-02-22T09:48:00",
                "sales_rank": 416
            },
            {
                "date": "2025-02-22T13:38:00",
                "sales_rank": 462
            },
            {
                "date": "2025-02-22T16:02:00",
                "sales_rank": 478
            },
            {
                "date": "2025-02-22T19:02:00",
                "sales_rank": 515
            },
            {
                "date": "2025-02-22T20:20:00",
                "sales_rank": 577
            },
            {
                "date": "2025-02-22T23:02:00",
                "sales_rank": 451
            },
            {
                "date": "2025-02-23T00:04:00",
                "sales_rank": 396
            },
            {
                "date": "2025-02-23T02:32:00",
                "sales_rank": 459
            },
            {
                "date": "2025-02-23T05:42:00",
                "sales_rank": 456
            },
            {
                "date": "2025-02-23T09:04:00",
                "sales_rank": 519
            },
            {
                "date": "2025-02-23T14:34:00",
                "sales_rank": 568
            },
            {
                "date": "2025-02-23T18:36:00",
                "sales_rank": 611
            },
            {
                "date": "2025-02-23T23:00:00",
                "sales_rank": 392
            },
            {
                "date": "2025-02-24T00:12:00",
                "sales_rank": 454
            },
            {
                "date": "2025-02-24T05:12:00",
                "sales_rank": 332
            },
            {
                "date": "2025-02-24T12:56:00",
                "sales_rank": 316
            },
            {
                "date": "2025-02-24T17:36:00",
                "sales_rank": 333
            },
            {
                "date": "2025-02-24T20:28:00",
                "sales_rank": 374
            },
            {
                "date": "2025-02-24T23:48:00",
                "sales_rank": 495
            },
            {
                "date": "2025-02-25T01:20:00",
                "sales_rank": 517
            },
            {
                "date": "2025-02-25T03:02:00",
                "sales_rank": 440
            },
            {
                "date": "2025-02-25T05:44:00",
                "sales_rank": 497
            },
            {
                "date": "2025-02-25T09:08:00",
                "sales_rank": 598
            },
            {
                "date": "2025-02-25T13:16:00",
                "sales_rank": 616
            },
            {
                "date": "2025-02-25T15:26:00",
                "sales_rank": 618
            },
            {
                "date": "2025-02-25T18:36:00",
                "sales_rank": 648
            },
            {
                "date": "2025-02-25T23:34:00",
                "sales_rank": 757
            },
            {
                "date": "2025-02-26T05:44:00",
                "sales_rank": 711
            },
            {
                "date": "2025-02-26T08:46:00",
                "sales_rank": 373
            },
            {
                "date": "2025-02-26T12:52:00",
                "sales_rank": 430
            },
            {
                "date": "2025-02-26T21:28:00",
                "sales_rank": 356
            },
            {
                "date": "2025-02-27T00:36:00",
                "sales_rank": 468
            },
            {
                "date": "2025-02-27T03:20:00",
                "sales_rank": 497
            },
            {
                "date": "2025-02-27T07:28:00",
                "sales_rank": 657
            },
            {
                "date": "2025-02-27T10:08:00",
                "sales_rank": 744
            },
            {
                "date": "2025-02-27T15:08:00",
                "sales_rank": 529
            },
            {
                "date": "2025-02-27T18:16:00",
                "sales_rank": 555
            },
            {
                "date": "2025-02-27T19:20:00",
                "sales_rank": 604
            },
            {
                "date": "2025-02-27T23:00:00",
                "sales_rank": 490
            },
            {
                "date": "2025-02-28T02:24:00",
                "sales_rank": 451
            },
            {
                "date": "2025-02-28T02:32:00",
                "sales_rank": 496
            },
            {
                "date": "2025-02-28T07:16:00",
                "sales_rank": 635
            },
            {
                "date": "2025-02-28T12:24:00",
                "sales_rank": 688
            },
            {
                "date": "2025-02-28T22:02:00",
                "sales_rank": 639
            },
            {
                "date": "2025-03-01T01:10:00",
                "sales_rank": 736
            },
            {
                "date": "2025-03-01T04:18:00",
                "sales_rank": 756
            },
            {
                "date": "2025-03-01T05:26:00",
                "sales_rank": 853
            },
            {
                "date": "2025-03-01T08:34:00",
                "sales_rank": 961
            },
            {
                "date": "2025-03-01T12:12:00",
                "sales_rank": 975
            },
            {
                "date": "2025-03-01T16:12:00",
                "sales_rank": 953
            },
            {
                "date": "2025-03-01T19:24:00",
                "sales_rank": 968
            },
            {
                "date": "2025-03-02T08:24:00",
                "sales_rank": 1387
            },
            {
                "date": "2025-03-02T11:54:00",
                "sales_rank": 1386
            },
            {
                "date": "2025-03-02T16:04:00",
                "sales_rank": 1344
            },
            {
                "date": "2025-03-03T00:20:00",
                "sales_rank": 796
            },
            {
                "date": "2025-03-03T02:26:00",
                "sales_rank": 601
            },
            {
                "date": "2025-03-03T07:36:00",
                "sales_rank": 700
            },
            {
                "date": "2025-03-03T11:44:00",
                "sales_rank": 851
            },
            {
                "date": "2025-03-04T04:16:00",
                "sales_rank": 1023
            },
            {
                "date": "2025-03-04T09:18:00",
                "sales_rank": 745
            },
            {
                "date": "2025-03-04T12:14:00",
                "sales_rank": 860
            },
            {
                "date": "2025-03-04T16:04:00",
                "sales_rank": 871
            },
            {
                "date": "2025-03-04T20:48:00",
                "sales_rank": 978
            },
            {
                "date": "2025-03-05T02:02:00",
                "sales_rank": 688
            },
            {
                "date": "2025-03-05T04:20:00",
                "sales_rank": 763
            },
            {
                "date": "2025-03-05T07:28:00",
                "sales_rank": 672
            },
            {
                "date": "2025-03-05T13:20:00",
                "sales_rank": 795
            },
            {
                "date": "2025-03-05T22:36:00",
                "sales_rank": 1040
            },
            {
                "date": "2025-03-06T14:14:00",
                "sales_rank": 954
            },
            {
                "date": "2025-03-06T17:08:00",
                "sales_rank": 985
            },
            {
                "date": "2025-03-07T01:26:00",
                "sales_rank": 1225
            },
            {
                "date": "2025-03-07T08:44:00",
                "sales_rank": 890
            },
            {
                "date": "2025-03-07T14:56:00",
                "sales_rank": 993
            },
            {
                "date": "2025-03-07T21:04:00",
                "sales_rank": 1117
            },
            {
                "date": "2025-03-08T06:58:00",
                "sales_rank": 1203
            },
            {
                "date": "2025-03-08T14:12:00",
                "sales_rank": 1180
            },
            {
                "date": "2025-03-08T18:00:00",
                "sales_rank": 1160
            },
            {
                "date": "2025-03-08T19:40:00",
                "sales_rank": 1184
            },
            {
                "date": "2025-03-08T20:44:00",
                "sales_rank": 1201
            },
            {
                "date": "2025-03-09T00:36:00",
                "sales_rank": 1357
            },
            {
                "date": "2025-03-09T23:22:00",
                "sales_rank": 1494
            },
            {
                "date": "2025-03-10T01:48:00",
                "sales_rank": 1530
            },
            {
                "date": "2025-03-10T08:22:00",
                "sales_rank": 1617
            },
            {
                "date": "2025-03-10T12:08:00",
                "sales_rank": 1646
            },
            {
                "date": "2025-03-10T13:56:00",
                "sales_rank": 1619
            },
            {
                "date": "2025-03-10T18:22:00",
                "sales_rank": 1599
            },
            {
                "date": "2025-03-10T21:56:00",
                "sales_rank": 1659
            },
            {
                "date": "2025-03-11T00:12:00",
                "sales_rank": 806
            },
            {
                "date": "2025-03-11T04:32:00",
                "sales_rank": 623
            },
            {
                "date": "2025-03-11T10:50:00",
                "sales_rank": 867
            },
            {
                "date": "2025-03-11T13:58:00",
                "sales_rank": 902
            },
            {
                "date": "2025-03-11T18:00:00",
                "sales_rank": 990
            },
            {
                "date": "2025-03-11T18:24:00",
                "sales_rank": 1043
            },
            {
                "date": "2025-03-11T21:40:00",
                "sales_rank": 1117
            },
            {
                "date": "2025-03-12T02:14:00",
                "sales_rank": 1336
            },
            {
                "date": "2025-03-12T08:26:00",
                "sales_rank": 1459
            },
            {
                "date": "2025-03-12T17:44:00",
                "sales_rank": 951
            },
            {
                "date": "2025-03-12T23:08:00",
                "sales_rank": 1166
            },
            {
                "date": "2025-03-13T05:58:00",
                "sales_rank": 1368
            },
            {
                "date": "2025-03-13T09:06:00",
                "sales_rank": 1467
            },
            {
                "date": "2025-03-13T12:14:00",
                "sales_rank": 1480
            },
            {
                "date": "2025-03-13T14:20:00",
                "sales_rank": 1481
            },
            {
                "date": "2025-03-13T18:46:00",
                "sales_rank": 711
            },
            {
                "date": "2025-03-14T01:52:00",
                "sales_rank": 1083
            },
            {
                "date": "2025-03-14T11:06:00",
                "sales_rank": 592
            },
            {
                "date": "2025-03-14T14:14:00",
                "sales_rank": 649
            },
            {
                "date": "2025-03-14T18:40:00",
                "sales_rank": 769
            },
            {
                "date": "2025-03-14T23:34:00",
                "sales_rank": 924
            },
            {
                "date": "2025-03-15T08:52:00",
                "sales_rank": 1263
            },
            {
                "date": "2025-03-15T20:58:00",
                "sales_rank": 1353
            },
            {
                "date": "2025-03-16T02:50:00",
                "sales_rank": 687
            },
            {
                "date": "2025-03-16T05:58:00",
                "sales_rank": 803
            },
            {
                "date": "2025-03-16T09:20:00",
                "sales_rank": 894
            },
            {
                "date": "2025-03-16T14:32:00",
                "sales_rank": 933
            },
            {
                "date": "2025-03-16T19:38:00",
                "sales_rank": 1019
            },
            {
                "date": "2025-03-16T23:48:00",
                "sales_rank": 1189
            },
            {
                "date": "2025-03-17T04:28:00",
                "sales_rank": 1370
            },
            {
                "date": "2025-03-17T07:36:00",
                "sales_rank": 1415
            },
            {
                "date": "2025-03-17T11:12:00",
                "sales_rank": 1432
            },
            {
                "date": "2025-03-17T18:12:00",
                "sales_rank": 1428
            },
            {
                "date": "2025-03-17T21:54:00",
                "sales_rank": 1448
            },
            {
                "date": "2025-03-18T01:02:00",
                "sales_rank": 538
            },
            {
                "date": "2025-03-18T03:46:00",
                "sales_rank": 620
            },
            {
                "date": "2025-03-18T05:58:00",
                "sales_rank": 571
            },
            {
                "date": "2025-03-18T09:16:00",
                "sales_rank": 685
            },
            {
                "date": "2025-03-18T12:40:00",
                "sales_rank": 707
            },
            {
                "date": "2025-03-18T16:40:00",
                "sales_rank": 739
            },
            {
                "date": "2025-03-18T18:00:00",
                "sales_rank": 808
            }
        ]
    }
}