{
    "asin": "B0CQLP2YZ7",
    "title": "Xiaomi Poco M6 Pro 4G LTE GSM (256GB + 8GB) 64MP Triple Camera 6.67\" Octa Core (Tmobile Mint Tello Global) Unlocked + (Bundle Fast Car Charger) (Black Global ROM)",
    "price_history": [
        {
            "date": "2024-01-19T06:12:00",
            "price": null
        }
    ],
    "sales_rank_history": {
        "2335752011": [
            {
                "date": "2025-01-08T22:00:00",
                "sales_rank": 102269
            },
            {
                "date": "2025-01-08T23:42:00",
                "sales_rank": 104315
            },
            {
                "date": "2025-01-09T02:50:00",
                "sales_rank": 107181
            },
            {
                "date": "2025-01-09T05:58:00",
                "sales_rank": 110589
            },
            {
                "date": "2025-01-09T09:06:00",
                "sales_rank": 114061
            },
            {
                "date": "2025-01-09T12:14:00",
                "sales_rank": 114861
            },
            {
                "date": "2025-01-09T15:22:00",
                "sales_rank": 115047
            },
            {
                "date": "2025-01-09T17:46:00",
                "sales_rank": 115412
            },
            {
                "date": "2025-01-09T20:52:00",
                "sales_rank": 117937
            },
            {
                "date": "2025-01-10T00:00:00",
                "sales_rank": 119908
            },
            {
                "date": "2025-01-10T03:48:00",
                "sales_rank": 123721
            },
            {
                "date": "2025-01-10T07:04:00",
                "sales_rank": 127969
            },
            {
                "date": "2025-01-10T11:02:00",
                "sales_rank": 128040
            },
            {
                "date": "2025-01-10T17:44:00",
                "sales_rank": 128812
            },
            {
                "date": "2025-01-10T20:50:00",
                "sales_rank": 130849
            },
            {
                "date": "2025-01-10T23:58:00",
                "sales_rank": 132586
            },
            {
                "date": "2025-01-11T03:06:00",
                "sales_rank": 135319
            },
            {
                "date": "2025-01-11T06:16:00",
                "sales_rank": 136838
            },
            {
                "date": "2025-01-11T13:12:00",
                "sales_rank": 139613
            },
            {
                "date": "2025-01-11T17:46:00",
                "sales_rank": 139601
            },
            {
                "date": "2025-01-11T20:54:00",
                "sales_rank": 139972
            },
            {
                "date": "2025-01-12T00:36:00",
                "sales_rank": 144670
            },
            {
                "date": "2025-01-12T02:52:00",
                "sales_rank": 146136
            },
            {
                "date": "2025-01-12T06:00:00",
                "sales_rank": 147625
            },
            {
                "date": "2025-01-12T09:08:00",
                "sales_rank": 149725
            },
            {
                "date": "2025-01-12T13:00:00",
                "sales_rank": 149818
            },
            {
                "date": "2025-01-12T17:08:00",
                "sales_rank": 148885
            },
            {
                "date": "2025-01-12T22:16:00",
                "sales_rank": 151016
            },
            {
                "date": "2025-01-13T02:54:00",
                "sales_rank": 152918
            },
            {
                "date": "2025-01-13T06:32:00",
                "sales_rank": 155685
            },
            {
                "date": "2025-01-13T16:10:00",
                "sales_rank": 61389
            },
            {
                "date": "2025-01-13T17:48:00",
                "sales_rank": 64176
            },
            {
                "date": "2025-01-13T21:36:00",
                "sales_rank": 67908
            },
            {
                "date": "2025-01-14T01:42:00",
                "sales_rank": 158367
            },
            {
                "date": "2025-01-14T05:16:00",
                "sales_rank": 160055
            },
            {
                "date": "2025-01-14T09:58:00",
                "sales_rank": 161971
            },
            {
                "date": "2025-01-14T16:52:00",
                "sales_rank": 160914
            },
            {
                "date": "2025-01-14T20:20:00",
                "sales_rank": 161179
            },
            {
                "date": "2025-01-15T00:26:00",
                "sales_rank": 162130
            },
            {
                "date": "2025-01-15T07:40:00",
                "sales_rank": 163731
            },
            {
                "date": "2025-01-15T14:44:00",
                "sales_rank": 163947
            },
            {
                "date": "2025-01-15T18:44:00",
                "sales_rank": 163540
            },
            {
                "date": "2025-01-15T22:54:00",
                "sales_rank": 164117
            },
            {
                "date": "2025-01-16T01:36:00",
                "sales_rank": 164388
            },
            {
                "date": "2025-01-16T02:46:00",
                "sales_rank": 164655
            },
            {
                "date": "2025-01-16T05:54:00",
                "sales_rank": 166631
            },
            {
                "date": "2025-01-16T10:06:00",
                "sales_rank": 167306
            },
            {
                "date": "2025-01-16T14:18:00",
                "sales_rank": 166679
            },
            {
                "date": "2025-01-16T17:44:00",
                "sales_rank": 166422
            },
            {
                "date": "2025-01-16T21:08:00",
                "sales_rank": 166602
            },
            {
                "date": "2025-01-17T03:20:00",
                "sales_rank": 168269
            },
            {
                "date": "2025-01-17T09:40:00",
                "sales_rank": 168934
            },
            {
                "date": "2025-01-17T11:18:00",
                "sales_rank": 168571
            },
            {
                "date": "2025-01-17T13:02:00",
                "sales_rank": 168112
            },
            {
                "date": "2025-01-17T16:10:00",
                "sales_rank": 167685
            },
            {
                "date": "2025-01-17T17:44:00",
                "sales_rank": 167454
            },
            {
                "date": "2025-01-17T22:22:00",
                "sales_rank": 170141
            },
            {
                "date": "2025-01-18T07:40:00",
                "sales_rank": 172598
            },
            {
                "date": "2025-01-18T13:26:00",
                "sales_rank": 171881
            },
            {
                "date": "2025-01-18T16:34:00",
                "sales_rank": 171047
            },
            {
                "date": "2025-01-18T17:46:00",
                "sales_rank": 170830
            },
            {
                "date": "2025-01-18T20:54:00",
                "sales_rank": 170943
            },
            {
                "date": "2025-01-18T23:28:00",
                "sales_rank": 173116
            },
            {
                "date": "2025-01-19T02:36:00",
                "sales_rank": 173856
            },
            {
                "date": "2025-01-19T05:42:00",
                "sales_rank": 175133
            },
            {
                "date": "2025-01-19T08:04:00",
                "sales_rank": 175793
            },
            {
                "date": "2025-01-19T11:36:00",
                "sales_rank": 175872
            },
            {
                "date": "2025-01-19T17:16:00",
                "sales_rank": 174039
            },
            {
                "date": "2025-01-19T20:24:00",
                "sales_rank": 53536
            },
            {
                "date": "2025-01-20T00:00:00",
                "sales_rank": 67250
            },
            {
                "date": "2025-01-20T04:36:00",
                "sales_rank": 47003
            },
            {
                "date": "2025-01-20T08:28:00",
                "sales_rank": 36687
            },
            {
                "date": "2025-01-20T12:54:00",
                "sales_rank": 41605
            },
            {
                "date": "2025-01-20T17:48:00",
                "sales_rank": 44258
            },
            {
                "date": "2025-01-20T19:56:00",
                "sales_rank": 52701
            },
            {
                "date": "2025-01-20T23:38:00",
                "sales_rank": 62410
            },
            {
                "date": "2025-01-21T03:44:00",
                "sales_rank": 71201
            },
            {
                "date": "2025-01-21T07:16:00",
                "sales_rank": 77344
            },
            {
                "date": "2025-01-21T14:28:00",
                "sales_rank": 81483
            },
            {
                "date": "2025-01-21T17:48:00",
                "sales_rank": 81526
            },
            {
                "date": "2025-01-22T00:36:00",
                "sales_rank": 87176
            },
            {
                "date": "2025-01-22T07:42:00",
                "sales_rank": 93919
            },
            {
                "date": "2025-01-22T13:40:00",
                "sales_rank": 99500
            },
            {
                "date": "2025-01-22T17:44:00",
                "sales_rank": 101130
            },
            {
                "date": "2025-01-22T20:52:00",
                "sales_rank": 39928
            },
            {
                "date": "2025-01-23T00:36:00",
                "sales_rank": 51179
            },
            {
                "date": "2025-01-23T04:44:00",
                "sales_rank": 62839
            },
            {
                "date": "2025-01-23T09:52:00",
                "sales_rank": 77429
            },
            {
                "date": "2025-01-23T16:56:00",
                "sales_rank": 82898
            },
            {
                "date": "2025-01-23T22:44:00",
                "sales_rank": 88069
            },
            {
                "date": "2025-01-24T00:18:00",
                "sales_rank": 90640
            },
            {
                "date": "2025-01-24T03:26:00",
                "sales_rank": 95746
            },
            {
                "date": "2025-01-24T07:52:00",
                "sales_rank": 46172
            },
            {
                "date": "2025-01-24T13:12:00",
                "sales_rank": 57337
            },
            {
                "date": "2025-01-24T17:44:00",
                "sales_rank": 60659
            },
            {
                "date": "2025-01-24T20:52:00",
                "sales_rank": 67544
            },
            {
                "date": "2025-01-25T04:20:00",
                "sales_rank": 85618
            },
            {
                "date": "2025-01-25T08:16:00",
                "sales_rank": 89344
            },
            {
                "date": "2025-01-25T12:00:00",
                "sales_rank": 47297
            },
            {
                "date": "2025-01-25T18:44:00",
                "sales_rank": 59399
            },
            {
                "date": "2025-01-25T20:48:00",
                "sales_rank": 64104
            },
            {
                "date": "2025-01-26T04:20:00",
                "sales_rank": 78480
            },
            {
                "date": "2025-01-26T09:16:00",
                "sales_rank": 86170
            },
            {
                "date": "2025-01-26T10:36:00",
                "sales_rank": 90883
            },
            {
                "date": "2025-01-26T15:04:00",
                "sales_rank": 91724
            },
            {
                "date": "2025-01-26T18:48:00",
                "sales_rank": 92222
            },
            {
                "date": "2025-01-26T22:04:00",
                "sales_rank": 96435
            },
            {
                "date": "2025-01-27T02:04:00",
                "sales_rank": 102106
            },
            {
                "date": "2025-01-27T09:20:00",
                "sales_rank": 109070
            },
            {
                "date": "2025-01-27T12:24:00",
                "sales_rank": 110511
            },
            {
                "date": "2025-01-27T18:52:00",
                "sales_rank": 111251
            },
            {
                "date": "2025-01-28T02:52:00",
                "sales_rank": 121578
            },
            {
                "date": "2025-01-28T07:16:00",
                "sales_rank": 125865
            },
            {
                "date": "2025-01-28T10:12:00",
                "sales_rank": 127276
            },
            {
                "date": "2025-01-28T18:44:00",
                "sales_rank": 128106
            },
            {
                "date": "2025-01-28T19:36:00",
                "sales_rank": 128880
            },
            {
                "date": "2025-01-29T02:20:00",
                "sales_rank": 132876
            },
            {
                "date": "2025-01-29T06:04:00",
                "sales_rank": 135854
            },
            {
                "date": "2025-01-29T09:36:00",
                "sales_rank": 138232
            },
            {
                "date": "2025-01-29T14:34:00",
                "sales_rank": 138608
            },
            {
                "date": "2025-01-29T17:28:00",
                "sales_rank": 138707
            },
            {
                "date": "2025-01-29T18:32:00",
                "sales_rank": 139205
            },
            {
                "date": "2025-01-29T19:50:00",
                "sales_rank": 43053
            },
            {
                "date": "2025-01-30T00:00:00",
                "sales_rank": 55234
            },
            {
                "date": "2025-01-30T05:08:00",
                "sales_rank": 69352
            },
            {
                "date": "2025-01-30T09:44:00",
                "sales_rank": 33422
            },
            {
                "date": "2025-01-30T15:24:00",
                "sales_rank": 36926
            },
            {
                "date": "2025-01-30T18:36:00",
                "sales_rank": 41595
            },
            {
                "date": "2025-01-30T23:06:00",
                "sales_rank": 57098
            },
            {
                "date": "2025-01-31T02:14:00",
                "sales_rank": 61647
            },
            {
                "date": "2025-01-31T05:40:00",
                "sales_rank": 69769
            },
            {
                "date": "2025-01-31T07:08:00",
                "sales_rank": 41890
            },
            {
                "date": "2025-01-31T16:40:00",
                "sales_rank": 50710
            },
            {
                "date": "2025-01-31T18:38:00",
                "sales_rank": 55242
            },
            {
                "date": "2025-01-31T21:46:00",
                "sales_rank": 63569
            },
            {
                "date": "2025-02-01T01:32:00",
                "sales_rank": 67870
            },
            {
                "date": "2025-02-01T05:58:00",
                "sales_rank": 78852
            },
            {
                "date": "2025-02-01T09:06:00",
                "sales_rank": 84058
            },
            {
                "date": "2025-02-01T12:00:00",
                "sales_rank": 84901
            },
            {
                "date": "2025-02-01T15:24:00",
                "sales_rank": 84271
            },
            {
                "date": "2025-02-01T18:44:00",
                "sales_rank": 84541
            },
            {
                "date": "2025-02-01T22:12:00",
                "sales_rank": 88082
            },
            {
                "date": "2025-02-02T02:18:00",
                "sales_rank": 93567
            },
            {
                "date": "2025-02-02T11:34:00",
                "sales_rank": 62309
            },
            {
                "date": "2025-02-02T15:12:00",
                "sales_rank": 64526
            },
            {
                "date": "2025-02-02T18:48:00",
                "sales_rank": 65680
            },
            {
                "date": "2025-02-02T21:54:00",
                "sales_rank": 37432
            },
            {
                "date": "2025-02-03T01:02:00",
                "sales_rank": 44734
            },
            {
                "date": "2025-02-03T04:54:00",
                "sales_rank": 60838
            },
            {
                "date": "2025-02-03T09:04:00",
                "sales_rank": 70477
            },
            {
                "date": "2025-02-03T15:32:00",
                "sales_rank": 73578
            },
            {
                "date": "2025-02-03T18:50:00",
                "sales_rank": 74898
            },
            {
                "date": "2025-02-03T23:48:00",
                "sales_rank": 81545
            },
            {
                "date": "2025-02-04T01:44:00",
                "sales_rank": 83845
            },
            {
                "date": "2025-02-04T02:46:00",
                "sales_rank": 86497
            },
            {
                "date": "2025-02-04T06:44:00",
                "sales_rank": 47347
            },
            {
                "date": "2025-02-04T10:08:00",
                "sales_rank": 38405
            },
            {
                "date": "2025-02-04T14:22:00",
                "sales_rank": 41997
            },
            {
                "date": "2025-02-04T18:24:00",
                "sales_rank": 46363
            },
            {
                "date": "2025-02-04T21:50:00",
                "sales_rank": 53885
            },
            {
                "date": "2025-02-05T00:58:00",
                "sales_rank": 58096
            },
            {
                "date": "2025-02-05T01:28:00",
                "sales_rank": 62048
            },
            {
                "date": "2025-02-05T06:48:00",
                "sales_rank": 71654
            },
            {
                "date": "2025-02-05T09:30:00",
                "sales_rank": 45607
            },
            {
                "date": "2025-02-05T13:08:00",
                "sales_rank": 49292
            },
            {
                "date": "2025-02-05T16:04:00",
                "sales_rank": 50310
            },
            {
                "date": "2025-02-05T18:44:00",
                "sales_rank": 55799
            },
            {
                "date": "2025-02-05T21:52:00",
                "sales_rank": 59213
            },
            {
                "date": "2025-02-06T03:20:00",
                "sales_rank": 68597
            },
            {
                "date": "2025-02-06T06:26:00",
                "sales_rank": 42852
            },
            {
                "date": "2025-02-06T10:22:00",
                "sales_rank": 51102
            },
            {
                "date": "2025-02-06T14:12:00",
                "sales_rank": 54413
            },
            {
                "date": "2025-02-06T17:22:00",
                "sales_rank": 56921
            },
            {
                "date": "2025-02-06T20:46:00",
                "sales_rank": 60258
            },
            {
                "date": "2025-02-06T22:32:00",
                "sales_rank": 65781
            },
            {
                "date": "2025-02-06T23:40:00",
                "sales_rank": 69436
            },
            {
                "date": "2025-02-07T04:30:00",
                "sales_rank": 76348
            },
            {
                "date": "2025-02-07T06:24:00",
                "sales_rank": 41189
            },
            {
                "date": "2025-02-07T12:12:00",
                "sales_rank": 53408
            },
            {
                "date": "2025-02-07T20:36:00",
                "sales_rank": 37817
            },
            {
                "date": "2025-02-07T21:14:00",
                "sales_rank": 41509
            },
            {
                "date": "2025-02-08T01:20:00",
                "sales_rank": 51803
            },
            {
                "date": "2025-02-08T06:32:00",
                "sales_rank": 64296
            },
            {
                "date": "2025-02-08T11:40:00",
                "sales_rank": 69565
            },
            {
                "date": "2025-02-08T15:32:00",
                "sales_rank": 69393
            },
            {
                "date": "2025-02-08T18:50:00",
                "sales_rank": 69469
            },
            {
                "date": "2025-02-08T21:58:00",
                "sales_rank": 31934
            },
            {
                "date": "2025-02-09T03:18:00",
                "sales_rank": 39355
            },
            {
                "date": "2025-02-09T10:32:00",
                "sales_rank": 55181
            },
            {
                "date": "2025-02-09T13:52:00",
                "sales_rank": 56980
            },
            {
                "date": "2025-02-09T17:46:00",
                "sales_rank": 57371
            },
            {
                "date": "2025-02-09T19:32:00",
                "sales_rank": 59709
            },
            {
                "date": "2025-02-10T00:22:00",
                "sales_rank": 69286
            },
            {
                "date": "2025-02-10T03:30:00",
                "sales_rank": 76420
            },
            {
                "date": "2025-02-10T08:14:00",
                "sales_rank": 45037
            },
            {
                "date": "2025-02-10T16:18:00",
                "sales_rank": 35504
            },
            {
                "date": "2025-02-10T20:04:00",
                "sales_rank": 40019
            },
            {
                "date": "2025-02-11T08:16:00",
                "sales_rank": 68418
            },
            {
                "date": "2025-02-11T12:56:00",
                "sales_rank": 71646
            },
            {
                "date": "2025-02-11T16:26:00",
                "sales_rank": 82325
            },
            {
                "date": "2025-02-11T18:50:00",
                "sales_rank": 83477
            },
            {
                "date": "2025-02-11T21:58:00",
                "sales_rank": 86213
            },
            {
                "date": "2025-02-12T00:04:00",
                "sales_rank": 87848
            },
            {
                "date": "2025-02-12T04:24:00",
                "sales_rank": 44215
            },
            {
                "date": "2025-02-12T16:48:00",
                "sales_rank": 44644
            },
            {
                "date": "2025-02-12T19:10:00",
                "sales_rank": 47698
            },
            {
                "date": "2025-02-12T21:00:00",
                "sales_rank": 32845
            },
            {
                "date": "2025-02-13T05:56:00",
                "sales_rank": 51786
            },
            {
                "date": "2025-02-13T09:24:00",
                "sales_rank": 29586
            },
            {
                "date": "2025-02-13T18:48:00",
                "sales_rank": 44471
            },
            {
                "date": "2025-02-13T22:28:00",
                "sales_rank": 51578
            },
            {
                "date": "2025-02-14T04:28:00",
                "sales_rank": 64751
            },
            {
                "date": "2025-02-14T10:20:00",
                "sales_rank": 73008
            },
            {
                "date": "2025-02-14T12:22:00",
                "sales_rank": 73488
            },
            {
                "date": "2025-02-14T14:24:00",
                "sales_rank": 73134
            },
            {
                "date": "2025-02-14T16:58:00",
                "sales_rank": 72785
            },
            {
                "date": "2025-02-14T22:14:00",
                "sales_rank": 76091
            },
            {
                "date": "2025-02-15T04:24:00",
                "sales_rank": 83401
            },
            {
                "date": "2025-02-15T06:40:00",
                "sales_rank": 87025
            },
            {
                "date": "2025-02-15T09:48:00",
                "sales_rank": 91107
            },
            {
                "date": "2025-02-15T13:04:00",
                "sales_rank": 92105
            },
            {
                "date": "2025-02-15T16:50:00",
                "sales_rank": 91864
            },
            {
                "date": "2025-02-15T19:52:00",
                "sales_rank": 92665
            },
            {
                "date": "2025-02-16T00:28:00",
                "sales_rank": 98801
            },
            {
                "date": "2025-02-16T04:54:00",
                "sales_rank": 49696
            },
            {
                "date": "2025-02-16T06:32:00",
                "sales_rank": 55428
            },
            {
                "date": "2025-02-16T12:28:00",
                "sales_rank": 65589
            },
            {
                "date": "2025-02-16T13:28:00",
                "sales_rank": 66917
            },
            {
                "date": "2025-02-16T17:38:00",
                "sales_rank": 67460
            },
            {
                "date": "2025-02-16T18:46:00",
                "sales_rank": 69105
            },
            {
                "date": "2025-02-16T21:54:00",
                "sales_rank": 70549
            },
            {
                "date": "2025-02-16T22:36:00",
                "sales_rank": 74140
            },
            {
                "date": "2025-02-17T01:56:00",
                "sales_rank": 78621
            },
            {
                "date": "2025-02-17T03:28:00",
                "sales_rank": 87886
            },
            {
                "date": "2025-02-17T06:36:00",
                "sales_rank": 91231
            },
            {
                "date": "2025-02-17T07:56:00",
                "sales_rank": 94407
            },
            {
                "date": "2025-02-17T11:04:00",
                "sales_rank": 48018
            },
            {
                "date": "2025-02-17T14:04:00",
                "sales_rank": 52572
            },
            {
                "date": "2025-02-17T16:40:00",
                "sales_rank": 53774
            },
            {
                "date": "2025-02-17T18:00:00",
                "sales_rank": 55679
            },
            {
                "date": "2025-02-17T19:54:00",
                "sales_rank": 59100
            },
            {
                "date": "2025-02-17T23:40:00",
                "sales_rank": 41381
            },
            {
                "date": "2025-02-18T02:36:00",
                "sales_rank": 26432
            },
            {
                "date": "2025-02-18T09:04:00",
                "sales_rank": 37051
            },
            {
                "date": "2025-02-18T13:04:00",
                "sales_rank": 39802
            },
            {
                "date": "2025-02-18T18:10:00",
                "sales_rank": 41710
            },
            {
                "date": "2025-02-18T21:14:00",
                "sales_rank": 45354
            },
            {
                "date": "2025-02-19T00:22:00",
                "sales_rank": 46991
            },
            {
                "date": "2025-02-19T03:30:00",
                "sales_rank": 60038
            },
            {
                "date": "2025-02-19T07:40:00",
                "sales_rank": 40840
            },
            {
                "date": "2025-02-19T18:42:00",
                "sales_rank": 51301
            },
            {
                "date": "2025-02-19T21:32:00",
                "sales_rank": 54776
            },
            {
                "date": "2025-02-20T01:20:00",
                "sales_rank": 37130
            },
            {
                "date": "2025-02-20T05:24:00",
                "sales_rank": 44826
            },
            {
                "date": "2025-02-20T10:30:00",
                "sales_rank": 40755
            },
            {
                "date": "2025-02-20T11:36:00",
                "sales_rank": 41982
            },
            {
                "date": "2025-02-20T14:14:00",
                "sales_rank": 43264
            },
            {
                "date": "2025-02-20T19:42:00",
                "sales_rank": 46149
            },
            {
                "date": "2025-02-20T20:54:00",
                "sales_rank": 52501
            },
            {
                "date": "2025-02-20T23:18:00",
                "sales_rank": 56933
            },
            {
                "date": "2025-02-21T01:54:00",
                "sales_rank": 59199
            },
            {
                "date": "2025-02-21T05:02:00",
                "sales_rank": 44178
            },
            {
                "date": "2025-02-21T08:04:00",
                "sales_rank": 48001
            },
            {
                "date": "2025-02-21T11:12:00",
                "sales_rank": 34387
            },
            {
                "date": "2025-02-21T14:48:00",
                "sales_rank": 37086
            },
            {
                "date": "2025-02-21T21:00:00",
                "sales_rank": 46623
            },
            {
                "date": "2025-02-22T08:16:00",
                "sales_rank": 39420
            },
            {
                "date": "2025-02-22T11:52:00",
                "sales_rank": 30712
            },
            {
                "date": "2025-02-22T16:02:00",
                "sales_rank": 26448
            },
            {
                "date": "2025-02-22T17:40:00",
                "sales_rank": 27722
            },
            {
                "date": "2025-02-22T19:02:00",
                "sales_rank": 23089
            },
            {
                "date": "2025-02-22T21:36:00",
                "sales_rank": 26116
            },
            {
                "date": "2025-02-22T23:02:00",
                "sales_rank": 29757
            },
            {
                "date": "2025-02-23T00:04:00",
                "sales_rank": 33526
            },
            {
                "date": "2025-02-23T02:32:00",
                "sales_rank": 27675
            },
            {
                "date": "2025-02-23T05:42:00",
                "sales_rank": 34156
            },
            {
                "date": "2025-02-23T10:36:00",
                "sales_rank": 30803
            },
            {
                "date": "2025-02-23T15:08:00",
                "sales_rank": 32421
            },
            {
                "date": "2025-02-23T18:16:00",
                "sales_rank": 35374
            },
            {
                "date": "2025-02-23T22:46:00",
                "sales_rank": 42093
            },
            {
                "date": "2025-02-24T01:54:00",
                "sales_rank": 45851
            },
            {
                "date": "2025-02-24T05:02:00",
                "sales_rank": 51609
            },
            {
                "date": "2025-02-24T08:10:00",
                "sales_rank": 60353
            },
            {
                "date": "2025-02-24T11:20:00",
                "sales_rank": 61319
            },
            {
                "date": "2025-02-24T14:28:00",
                "sales_rank": 59378
            },
            {
                "date": "2025-02-24T17:32:00",
                "sales_rank": 58692
            },
            {
                "date": "2025-02-24T20:44:00",
                "sales_rank": 61224
            },
            {
                "date": "2025-02-25T00:20:00",
                "sales_rank": 68246
            },
            {
                "date": "2025-02-25T02:16:00",
                "sales_rank": 69895
            },
            {
                "date": "2025-02-25T07:04:00",
                "sales_rank": 80431
            },
            {
                "date": "2025-02-25T11:48:00",
                "sales_rank": 48746
            },
            {
                "date": "2025-02-25T18:24:00",
                "sales_rank": 55743
            },
            {
                "date": "2025-02-26T02:40:00",
                "sales_rank": 71520
            },
            {
                "date": "2025-02-26T04:24:00",
                "sales_rank": 73298
            },
            {
                "date": "2025-02-26T06:14:00",
                "sales_rank": 77950
            },
            {
                "date": "2025-02-26T09:22:00",
                "sales_rank": 83079
            },
            {
                "date": "2025-02-26T12:30:00",
                "sales_rank": 83646
            },
            {
                "date": "2025-02-26T16:00:00",
                "sales_rank": 82520
            },
            {
                "date": "2025-02-26T21:08:00",
                "sales_rank": 46544
            },
            {
                "date": "2025-02-27T01:02:00",
                "sales_rank": 32752
            },
            {
                "date": "2025-02-27T02:20:00",
                "sales_rank": 34954
            },
            {
                "date": "2025-02-27T03:20:00",
                "sales_rank": 41435
            },
            {
                "date": "2025-02-27T09:56:00",
                "sales_rank": 54625
            },
            {
                "date": "2025-02-27T14:00:00",
                "sales_rank": 57233
            },
            {
                "date": "2025-02-27T17:48:00",
                "sales_rank": 59420
            },
            {
                "date": "2025-02-27T20:22:00",
                "sales_rank": 62471
            },
            {
                "date": "2025-02-28T02:32:00",
                "sales_rank": 77484
            },
            {
                "date": "2025-02-28T05:40:00",
                "sales_rank": 81119
            },
            {
                "date": "2025-02-28T11:24:00",
                "sales_rank": 88022
            },
            {
                "date": "2025-02-28T17:36:00",
                "sales_rank": 86950
            },
            {
                "date": "2025-02-28T21:40:00",
                "sales_rank": 89492
            },
            {
                "date": "2025-03-01T02:10:00",
                "sales_rank": 92211
            },
            {
                "date": "2025-03-01T05:18:00",
                "sales_rank": 47937
            },
            {
                "date": "2025-03-01T08:26:00",
                "sales_rank": 58559
            },
            {
                "date": "2025-03-01T15:16:00",
                "sales_rank": 64144
            },
            {
                "date": "2025-03-02T03:40:00",
                "sales_rank": 40094
            },
            {
                "date": "2025-03-02T07:44:00",
                "sales_rank": 48859
            },
            {
                "date": "2025-03-02T10:56:00",
                "sales_rank": 53135
            },
            {
                "date": "2025-03-02T14:28:00",
                "sales_rank": 54025
            },
            {
                "date": "2025-03-02T18:12:00",
                "sales_rank": 32966
            },
            {
                "date": "2025-03-03T03:28:00",
                "sales_rank": 55268
            },
            {
                "date": "2025-03-03T05:36:00",
                "sales_rank": 60567
            },
            {
                "date": "2025-03-03T10:40:00",
                "sales_rank": 70054
            },
            {
                "date": "2025-03-03T14:48:00",
                "sales_rank": 69058
            },
            {
                "date": "2025-03-03T17:14:00",
                "sales_rank": 68568
            },
            {
                "date": "2025-03-03T20:22:00",
                "sales_rank": 71688
            },
            {
                "date": "2025-03-03T23:30:00",
                "sales_rank": 77579
            },
            {
                "date": "2025-03-04T03:38:00",
                "sales_rank": 87153
            },
            {
                "date": "2025-03-04T07:20:00",
                "sales_rank": 89002
            },
            {
                "date": "2025-03-04T09:32:00",
                "sales_rank": 92449
            },
            {
                "date": "2025-03-04T11:24:00",
                "sales_rank": 95966
            },
            {
                "date": "2025-03-04T14:20:00",
                "sales_rank": 95745
            },
            {
                "date": "2025-03-04T16:08:00",
                "sales_rank": 41678
            },
            {
                "date": "2025-03-04T18:12:00",
                "sales_rank": 44456
            },
            {
                "date": "2025-03-04T22:52:00",
                "sales_rank": 32660
            },
            {
                "date": "2025-03-05T00:52:00",
                "sales_rank": 41071
            },
            {
                "date": "2025-03-05T04:42:00",
                "sales_rank": 45275
            },
            {
                "date": "2025-03-05T07:50:00",
                "sales_rank": 55827
            },
            {
                "date": "2025-03-05T10:58:00",
                "sales_rank": 40876
            },
            {
                "date": "2025-03-05T14:06:00",
                "sales_rank": 41901
            },
            {
                "date": "2025-03-05T17:44:00",
                "sales_rank": 44812
            },
            {
                "date": "2025-03-06T00:42:00",
                "sales_rank": 57038
            },
            {
                "date": "2025-03-06T07:00:00",
                "sales_rank": 44763
            },
            {
                "date": "2025-03-06T11:34:00",
                "sales_rank": 51455
            },
            {
                "date": "2025-03-06T14:42:00",
                "sales_rank": 53475
            },
            {
                "date": "2025-03-06T21:44:00",
                "sales_rank": 55831
            },
            {
                "date": "2025-03-07T00:54:00",
                "sales_rank": 63250
            },
            {
                "date": "2025-03-07T04:02:00",
                "sales_rank": 66779
            },
            {
                "date": "2025-03-07T07:10:00",
                "sales_rank": 73494
            },
            {
                "date": "2025-03-07T10:48:00",
                "sales_rank": 78684
            },
            {
                "date": "2025-03-07T17:16:00",
                "sales_rank": 77032
            },
            {
                "date": "2025-03-08T01:48:00",
                "sales_rank": 57460
            },
            {
                "date": "2025-03-08T11:06:00",
                "sales_rank": 74740
            },
            {
                "date": "2025-03-08T19:08:00",
                "sales_rank": 75069
            },
            {
                "date": "2025-03-08T20:30:00",
                "sales_rank": 77331
            },
            {
                "date": "2025-03-08T23:38:00",
                "sales_rank": 80000
            },
            {
                "date": "2025-03-09T02:46:00",
                "sales_rank": 84253
            },
            {
                "date": "2025-03-10T05:54:00",
                "sales_rank": 85544
            },
            {
                "date": "2025-03-10T10:06:00",
                "sales_rank": 89754
            },
            {
                "date": "2025-03-10T13:14:00",
                "sales_rank": 90774
            },
            {
                "date": "2025-03-10T16:46:00",
                "sales_rank": 90640
            },
            {
                "date": "2025-03-10T18:28:00",
                "sales_rank": 41308
            },
            {
                "date": "2025-03-10T21:36:00",
                "sales_rank": 48339
            },
            {
                "date": "2025-03-11T02:28:00",
                "sales_rank": 64072
            },
            {
                "date": "2025-03-11T07:28:00",
                "sales_rank": 74345
            },
            {
                "date": "2025-03-11T10:36:00",
                "sales_rank": 77478
            },
            {
                "date": "2025-03-11T13:40:00",
                "sales_rank": 78140
            },
            {
                "date": "2025-03-11T16:46:00",
                "sales_rank": 78689
            },
            {
                "date": "2025-03-11T19:32:00",
                "sales_rank": 80168
            },
            {
                "date": "2025-03-11T22:36:00",
                "sales_rank": 82109
            },
            {
                "date": "2025-03-12T01:44:00",
                "sales_rank": 85923
            },
            {
                "date": "2025-03-12T06:24:00",
                "sales_rank": 94163
            },
            {
                "date": "2025-03-12T13:36:00",
                "sales_rank": 99289
            },
            {
                "date": "2025-03-12T18:32:00",
                "sales_rank": 101189
            },
            {
                "date": "2025-03-12T22:08:00",
                "sales_rank": 102979
            },
            {
                "date": "2025-03-13T05:20:00",
                "sales_rank": 110526
            },
            {
                "date": "2025-03-13T11:02:00",
                "sales_rank": 58548
            },
            {
                "date": "2025-03-13T16:44:00",
                "sales_rank": 64126
            },
            {
                "date": "2025-03-13T20:08:00",
                "sales_rank": 69511
            },
            {
                "date": "2025-03-13T23:48:00",
                "sales_rank": 78330
            },
            {
                "date": "2025-03-14T11:10:00",
                "sales_rank": 96789
            },
            {
                "date": "2025-03-14T15:24:00",
                "sales_rank": 97667
            },
            {
                "date": "2025-03-14T19:26:00",
                "sales_rank": 100143
            },
            {
                "date": "2025-03-14T23:30:00",
                "sales_rank": 104260
            },
            {
                "date": "2025-03-15T01:46:00",
                "sales_rank": 107710
            },
            {
                "date": "2025-03-15T04:54:00",
                "sales_rank": 109806
            },
            {
                "date": "2025-03-15T09:56:00",
                "sales_rank": 113712
            },
            {
                "date": "2025-03-15T23:00:00",
                "sales_rank": 118661
            },
            {
                "date": "2025-03-16T11:04:00",
                "sales_rank": 129168
            },
            {
                "date": "2025-03-16T14:32:00",
                "sales_rank": 128947
            },
            {
                "date": "2025-03-16T18:20:00",
                "sales_rank": 128514
            },
            {
                "date": "2025-03-17T00:52:00",
                "sales_rank": 132957
            },
            {
                "date": "2025-03-17T07:50:00",
                "sales_rank": 138159
            },
            {
                "date": "2025-03-17T10:58:00",
                "sales_rank": 139210
            },
            {
                "date": "2025-03-17T14:06:00",
                "sales_rank": 138525
            },
            {
                "date": "2025-03-17T17:46:00",
                "sales_rank": 138658
            },
            {
                "date": "2025-03-17T20:54:00",
                "sales_rank": 141443
            },
            {
                "date": "2025-03-18T00:34:00",
                "sales_rank": 142947
            },
            {
                "date": "2025-03-18T02:52:00",
                "sales_rank": 143740
            },
            {
                "date": "2025-03-18T08:12:00",
                "sales_rank": 145637
            },
            {
                "date": "2025-03-18T17:42:00",
                "sales_rank": 145130
            }
        ],
        "7072561011": [
            {
                "date": "2025-01-08T16:52:00",
                "sales_rank": 1707
            },
            {
                "date": "2025-01-08T22:00:00",
                "sales_rank": 1777
            },
            {
                "date": "2025-01-08T23:42:00",
                "sales_rank": 1818
            },
            {
                "date": "2025-01-09T02:50:00",
                "sales_rank": 1875
            },
            {
                "date": "2025-01-09T05:58:00",
                "sales_rank": 1943
            },
            {
                "date": "2025-01-09T09:06:00",
                "sales_rank": 1994
            },
            {
                "date": "2025-01-09T12:14:00",
                "sales_rank": 2013
            },
            {
                "date": "2025-01-09T15:22:00",
                "sales_rank": 2017
            },
            {
                "date": "2025-01-09T17:46:00",
                "sales_rank": 2034
            },
            {
                "date": "2025-01-09T20:52:00",
                "sales_rank": 2064
            },
            {
                "date": "2025-01-10T00:00:00",
                "sales_rank": 2097
            },
            {
                "date": "2025-01-10T03:48:00",
                "sales_rank": 2153
            },
            {
                "date": "2025-01-10T07:04:00",
                "sales_rank": 2208
            },
            {
                "date": "2025-01-10T11:02:00",
                "sales_rank": 2240
            },
            {
                "date": "2025-01-10T17:44:00",
                "sales_rank": 2252
            },
            {
                "date": "2025-01-10T20:50:00",
                "sales_rank": 2281
            },
            {
                "date": "2025-01-10T23:58:00",
                "sales_rank": 2318
            },
            {
                "date": "2025-01-11T03:06:00",
                "sales_rank": 2357
            },
            {
                "date": "2025-01-11T06:16:00",
                "sales_rank": 2381
            },
            {
                "date": "2025-01-11T13:12:00",
                "sales_rank": 2409
            },
            {
                "date": "2025-01-11T17:46:00",
                "sales_rank": 2413
            },
            {
                "date": "2025-01-11T20:54:00",
                "sales_rank": 2426
            },
            {
                "date": "2025-01-12T00:36:00",
                "sales_rank": 2479
            },
            {
                "date": "2025-01-12T02:52:00",
                "sales_rank": 2492
            },
            {
                "date": "2025-01-12T06:00:00",
                "sales_rank": 2504
            },
            {
                "date": "2025-01-12T09:08:00",
                "sales_rank": 2534
            },
            {
                "date": "2025-01-12T13:00:00",
                "sales_rank": 2546
            },
            {
                "date": "2025-01-12T17:08:00",
                "sales_rank": 2542
            },
            {
                "date": "2025-01-12T22:16:00",
                "sales_rank": 2580
            },
            {
                "date": "2025-01-13T02:54:00",
                "sales_rank": 2613
            },
            {
                "date": "2025-01-13T06:32:00",
                "sales_rank": 2629
            },
            {
                "date": "2025-01-13T16:10:00",
                "sales_rank": 1042
            },
            {
                "date": "2025-01-13T17:48:00",
                "sales_rank": 1092
            },
            {
                "date": "2025-01-13T21:36:00",
                "sales_rank": 1160
            },
            {
                "date": "2025-01-14T01:42:00",
                "sales_rank": 2678
            },
            {
                "date": "2025-01-14T05:16:00",
                "sales_rank": 2704
            },
            {
                "date": "2025-01-14T09:58:00",
                "sales_rank": 2729
            },
            {
                "date": "2025-01-14T16:52:00",
                "sales_rank": 2717
            },
            {
                "date": "2025-01-14T20:20:00",
                "sales_rank": 2721
            },
            {
                "date": "2025-01-15T00:26:00",
                "sales_rank": 2743
            },
            {
                "date": "2025-01-15T07:40:00",
                "sales_rank": 2784
            },
            {
                "date": "2025-01-15T14:44:00",
                "sales_rank": 2786
            },
            {
                "date": "2025-01-15T18:44:00",
                "sales_rank": 2790
            },
            {
                "date": "2025-01-15T22:54:00",
                "sales_rank": 2806
            },
            {
                "date": "2025-01-16T01:36:00",
                "sales_rank": 2811
            },
            {
                "date": "2025-01-16T02:46:00",
                "sales_rank": 2821
            },
            {
                "date": "2025-01-16T05:54:00",
                "sales_rank": 2847
            },
            {
                "date": "2025-01-16T10:06:00",
                "sales_rank": 2854
            },
            {
                "date": "2025-01-16T14:18:00",
                "sales_rank": 2848
            },
            {
                "date": "2025-01-16T17:44:00",
                "sales_rank": 2841
            },
            {
                "date": "2025-01-16T21:08:00",
                "sales_rank": 2847
            },
            {
                "date": "2025-01-17T03:20:00",
                "sales_rank": 2901
            },
            {
                "date": "2025-01-17T09:40:00",
                "sales_rank": 2919
            },
            {
                "date": "2025-01-17T11:18:00",
                "sales_rank": 2923
            },
            {
                "date": "2025-01-17T13:02:00",
                "sales_rank": 2915
            },
            {
                "date": "2025-01-17T16:10:00",
                "sales_rank": 2907
            },
            {
                "date": "2025-01-17T17:44:00",
                "sales_rank": 2906
            },
            {
                "date": "2025-01-17T22:22:00",
                "sales_rank": 2942
            },
            {
                "date": "2025-01-18T07:40:00",
                "sales_rank": 2977
            },
            {
                "date": "2025-01-18T13:26:00",
                "sales_rank": 2952
            },
            {
                "date": "2025-01-18T16:34:00",
                "sales_rank": 2945
            },
            {
                "date": "2025-01-18T17:46:00",
                "sales_rank": 2942
            },
            {
                "date": "2025-01-18T20:54:00",
                "sales_rank": 2945
            },
            {
                "date": "2025-01-18T23:28:00",
                "sales_rank": 2970
            },
            {
                "date": "2025-01-19T02:36:00",
                "sales_rank": 2979
            },
            {
                "date": "2025-01-19T05:42:00",
                "sales_rank": 2980
            },
            {
                "date": "2025-01-19T11:36:00",
                "sales_rank": 2977
            },
            {
                "date": "2025-01-19T17:16:00",
                "sales_rank": 2955
            },
            {
                "date": "2025-01-19T20:24:00",
                "sales_rank": 938
            },
            {
                "date": "2025-01-20T00:00:00",
                "sales_rank": 1174
            },
            {
                "date": "2025-01-20T04:36:00",
                "sales_rank": 812
            },
            {
                "date": "2025-01-20T08:28:00",
                "sales_rank": 635
            },
            {
                "date": "2025-01-20T12:54:00",
                "sales_rank": 701
            },
            {
                "date": "2025-01-20T17:48:00",
                "sales_rank": 751
            },
            {
                "date": "2025-01-20T19:56:00",
                "sales_rank": 909
            },
            {
                "date": "2025-01-20T23:38:00",
                "sales_rank": 1089
            },
            {
                "date": "2025-01-21T03:44:00",
                "sales_rank": 1270
            },
            {
                "date": "2025-01-21T07:16:00",
                "sales_rank": 1381
            },
            {
                "date": "2025-01-21T14:28:00",
                "sales_rank": 1442
            },
            {
                "date": "2025-01-21T17:48:00",
                "sales_rank": 1440
            },
            {
                "date": "2025-01-22T00:36:00",
                "sales_rank": 1560
            },
            {
                "date": "2025-01-22T07:42:00",
                "sales_rank": 1692
            },
            {
                "date": "2025-01-22T13:40:00",
                "sales_rank": 1775
            },
            {
                "date": "2025-01-22T17:44:00",
                "sales_rank": 1807
            },
            {
                "date": "2025-01-22T20:52:00",
                "sales_rank": 732
            },
            {
                "date": "2025-01-23T00:36:00",
                "sales_rank": 947
            },
            {
                "date": "2025-01-23T04:44:00",
                "sales_rank": 1183
            },
            {
                "date": "2025-01-23T09:52:00",
                "sales_rank": 1436
            },
            {
                "date": "2025-01-23T16:56:00",
                "sales_rank": 1542
            },
            {
                "date": "2025-01-23T22:44:00",
                "sales_rank": 1610
            },
            {
                "date": "2025-01-24T00:18:00",
                "sales_rank": 1669
            },
            {
                "date": "2025-01-24T03:26:00",
                "sales_rank": 1750
            },
            {
                "date": "2025-01-24T07:52:00",
                "sales_rank": 824
            },
            {
                "date": "2025-01-24T13:12:00",
                "sales_rank": 1035
            },
            {
                "date": "2025-01-24T17:44:00",
                "sales_rank": 1096
            },
            {
                "date": "2025-01-24T20:52:00",
                "sales_rank": 1225
            },
            {
                "date": "2025-01-25T04:20:00",
                "sales_rank": 1531
            },
            {
                "date": "2025-01-25T08:16:00",
                "sales_rank": 1588
            },
            {
                "date": "2025-01-25T12:00:00",
                "sales_rank": 875
            },
            {
                "date": "2025-01-25T18:44:00",
                "sales_rank": 1080
            },
            {
                "date": "2025-01-25T20:48:00",
                "sales_rank": 1157
            },
            {
                "date": "2025-01-26T04:20:00",
                "sales_rank": 1406
            },
            {
                "date": "2025-01-26T09:16:00",
                "sales_rank": 1555
            },
            {
                "date": "2025-01-26T10:36:00",
                "sales_rank": 1623
            },
            {
                "date": "2025-01-26T15:04:00",
                "sales_rank": 1637
            },
            {
                "date": "2025-01-26T18:48:00",
                "sales_rank": 1636
            },
            {
                "date": "2025-01-26T22:04:00",
                "sales_rank": 1699
            },
            {
                "date": "2025-01-27T02:04:00",
                "sales_rank": 1776
            },
            {
                "date": "2025-01-27T09:20:00",
                "sales_rank": 1896
            },
            {
                "date": "2025-01-27T12:24:00",
                "sales_rank": 1924
            },
            {
                "date": "2025-01-27T18:52:00",
                "sales_rank": 1939
            },
            {
                "date": "2025-01-28T02:52:00",
                "sales_rank": 2131
            },
            {
                "date": "2025-01-28T07:16:00",
                "sales_rank": 2193
            },
            {
                "date": "2025-01-28T10:12:00",
                "sales_rank": 2221
            },
            {
                "date": "2025-01-28T18:44:00",
                "sales_rank": 2248
            },
            {
                "date": "2025-01-28T19:36:00",
                "sales_rank": 2259
            },
            {
                "date": "2025-01-29T02:20:00",
                "sales_rank": 2315
            },
            {
                "date": "2025-01-29T06:04:00",
                "sales_rank": 2390
            },
            {
                "date": "2025-01-29T09:36:00",
                "sales_rank": 2432
            },
            {
                "date": "2025-01-29T14:34:00",
                "sales_rank": 2464
            },
            {
                "date": "2025-01-29T17:28:00",
                "sales_rank": 2467
            },
            {
                "date": "2025-01-29T18:32:00",
                "sales_rank": 2478
            },
            {
                "date": "2025-01-29T19:50:00",
                "sales_rank": 782
            },
            {
                "date": "2025-01-30T00:00:00",
                "sales_rank": 1065
            },
            {
                "date": "2025-01-30T05:08:00",
                "sales_rank": 1304
            },
            {
                "date": "2025-01-30T09:44:00",
                "sales_rank": 609
            },
            {
                "date": "2025-01-30T15:24:00",
                "sales_rank": 682
            },
            {
                "date": "2025-01-30T18:36:00",
                "sales_rank": 765
            },
            {
                "date": "2025-01-30T23:06:00",
                "sales_rank": 1062
            },
            {
                "date": "2025-01-31T02:14:00",
                "sales_rank": 1155
            },
            {
                "date": "2025-01-31T05:40:00",
                "sales_rank": 1320
            },
            {
                "date": "2025-01-31T07:08:00",
                "sales_rank": 771
            },
            {
                "date": "2025-01-31T16:40:00",
                "sales_rank": 946
            },
            {
                "date": "2025-01-31T18:38:00",
                "sales_rank": 1026
            },
            {
                "date": "2025-01-31T21:46:00",
                "sales_rank": 1177
            },
            {
                "date": "2025-02-01T01:32:00",
                "sales_rank": 1259
            },
            {
                "date": "2025-02-01T05:58:00",
                "sales_rank": 1433
            },
            {
                "date": "2025-02-01T09:06:00",
                "sales_rank": 1530
            },
            {
                "date": "2025-02-01T12:00:00",
                "sales_rank": 1537
            },
            {
                "date": "2025-02-01T15:24:00",
                "sales_rank": 1544
            },
            {
                "date": "2025-02-01T18:44:00",
                "sales_rank": 1555
            },
            {
                "date": "2025-02-01T22:12:00",
                "sales_rank": 1587
            },
            {
                "date": "2025-02-02T02:18:00",
                "sales_rank": 1679
            },
            {
                "date": "2025-02-02T11:34:00",
                "sales_rank": 1109
            },
            {
                "date": "2025-02-02T15:12:00",
                "sales_rank": 1166
            },
            {
                "date": "2025-02-02T18:48:00",
                "sales_rank": 1199
            },
            {
                "date": "2025-02-02T21:54:00",
                "sales_rank": 634
            },
            {
                "date": "2025-02-03T01:02:00",
                "sales_rank": 805
            },
            {
                "date": "2025-02-03T04:54:00",
                "sales_rank": 1102
            },
            {
                "date": "2025-02-03T09:04:00",
                "sales_rank": 1259
            },
            {
                "date": "2025-02-03T15:32:00",
                "sales_rank": 1307
            },
            {
                "date": "2025-02-03T18:50:00",
                "sales_rank": 1340
            },
            {
                "date": "2025-02-03T23:48:00",
                "sales_rank": 1480
            },
            {
                "date": "2025-02-04T01:44:00",
                "sales_rank": 1517
            },
            {
                "date": "2025-02-04T02:46:00",
                "sales_rank": 1567
            },
            {
                "date": "2025-02-04T06:44:00",
                "sales_rank": 894
            },
            {
                "date": "2025-02-04T10:08:00",
                "sales_rank": 703
            },
            {
                "date": "2025-02-04T14:22:00",
                "sales_rank": 763
            },
            {
                "date": "2025-02-04T18:24:00",
                "sales_rank": 842
            },
            {
                "date": "2025-02-04T21:50:00",
                "sales_rank": 983
            },
            {
                "date": "2025-02-05T00:58:00",
                "sales_rank": 1070
            },
            {
                "date": "2025-02-05T01:28:00",
                "sales_rank": 1144
            },
            {
                "date": "2025-02-05T06:48:00",
                "sales_rank": 1311
            },
            {
                "date": "2025-02-05T09:30:00",
                "sales_rank": 850
            },
            {
                "date": "2025-02-05T13:08:00",
                "sales_rank": 908
            },
            {
                "date": "2025-02-05T16:04:00",
                "sales_rank": 918
            },
            {
                "date": "2025-02-05T18:44:00",
                "sales_rank": 1023
            },
            {
                "date": "2025-02-05T21:52:00",
                "sales_rank": 1094
            },
            {
                "date": "2025-02-06T03:20:00",
                "sales_rank": 1267
            },
            {
                "date": "2025-02-06T06:26:00",
                "sales_rank": 797
            },
            {
                "date": "2025-02-06T10:22:00",
                "sales_rank": 964
            },
            {
                "date": "2025-02-06T14:12:00",
                "sales_rank": 1005
            },
            {
                "date": "2025-02-06T17:22:00",
                "sales_rank": 1070
            },
            {
                "date": "2025-02-06T20:46:00",
                "sales_rank": 1142
            },
            {
                "date": "2025-02-06T22:32:00",
                "sales_rank": 1238
            },
            {
                "date": "2025-02-06T23:40:00",
                "sales_rank": 1298
            },
            {
                "date": "2025-02-07T04:30:00",
                "sales_rank": 1412
            },
            {
                "date": "2025-02-07T06:24:00",
                "sales_rank": 765
            },
            {
                "date": "2025-02-07T12:12:00",
                "sales_rank": 1002
            },
            {
                "date": "2025-02-07T20:36:00",
                "sales_rank": 697
            },
            {
                "date": "2025-02-07T21:14:00",
                "sales_rank": 753
            },
            {
                "date": "2025-02-08T01:20:00",
                "sales_rank": 956
            },
            {
                "date": "2025-02-08T06:32:00",
                "sales_rank": 1197
            },
            {
                "date": "2025-02-08T11:40:00",
                "sales_rank": 1269
            },
            {
                "date": "2025-02-08T15:32:00",
                "sales_rank": 1257
            },
            {
                "date": "2025-02-08T18:50:00",
                "sales_rank": 1272
            },
            {
                "date": "2025-02-08T21:58:00",
                "sales_rank": 573
            },
            {
                "date": "2025-02-09T03:18:00",
                "sales_rank": 730
            },
            {
                "date": "2025-02-09T10:32:00",
                "sales_rank": 996
            },
            {
                "date": "2025-02-09T13:52:00",
                "sales_rank": 1050
            },
            {
                "date": "2025-02-09T17:46:00",
                "sales_rank": 1056
            },
            {
                "date": "2025-02-09T19:32:00",
                "sales_rank": 1094
            },
            {
                "date": "2025-02-10T00:22:00",
                "sales_rank": 1240
            },
            {
                "date": "2025-02-10T03:30:00",
                "sales_rank": 1363
            },
            {
                "date": "2025-02-10T08:14:00",
                "sales_rank": 775
            },
            {
                "date": "2025-02-10T16:18:00",
                "sales_rank": 626
            },
            {
                "date": "2025-02-10T20:04:00",
                "sales_rank": 707
            },
            {
                "date": "2025-02-11T08:16:00",
                "sales_rank": 1283
            },
            {
                "date": "2025-02-11T12:56:00",
                "sales_rank": 1323
            },
            {
                "date": "2025-02-11T16:26:00",
                "sales_rank": 1533
            },
            {
                "date": "2025-02-11T18:50:00",
                "sales_rank": 1559
            },
            {
                "date": "2025-02-11T21:58:00",
                "sales_rank": 1590
            },
            {
                "date": "2025-02-12T00:04:00",
                "sales_rank": 1621
            },
            {
                "date": "2025-02-12T04:24:00",
                "sales_rank": 841
            },
            {
                "date": "2025-02-12T16:48:00",
                "sales_rank": 832
            },
            {
                "date": "2025-02-12T19:10:00",
                "sales_rank": 887
            },
            {
                "date": "2025-02-12T21:00:00",
                "sales_rank": 605
            },
            {
                "date": "2025-02-13T05:56:00",
                "sales_rank": 957
            },
            {
                "date": "2025-02-13T09:24:00",
                "sales_rank": 523
            },
            {
                "date": "2025-02-13T18:48:00",
                "sales_rank": 810
            },
            {
                "date": "2025-02-13T22:28:00",
                "sales_rank": 951
            },
            {
                "date": "2025-02-14T04:28:00",
                "sales_rank": 1179
            },
            {
                "date": "2025-02-14T10:20:00",
                "sales_rank": 1359
            },
            {
                "date": "2025-02-14T12:22:00",
                "sales_rank": 1377
            },
            {
                "date": "2025-02-14T14:24:00",
                "sales_rank": 1373
            },
            {
                "date": "2025-02-14T16:58:00",
                "sales_rank": 1377
            },
            {
                "date": "2025-02-14T22:14:00",
                "sales_rank": 1467
            },
            {
                "date": "2025-02-15T04:24:00",
                "sales_rank": 1594
            },
            {
                "date": "2025-02-15T06:40:00",
                "sales_rank": 1666
            },
            {
                "date": "2025-02-15T09:48:00",
                "sales_rank": 1734
            },
            {
                "date": "2025-02-15T16:50:00",
                "sales_rank": 1724
            },
            {
                "date": "2025-02-15T19:52:00",
                "sales_rank": 1733
            },
            {
                "date": "2025-02-16T00:28:00",
                "sales_rank": 1801
            },
            {
                "date": "2025-02-16T04:54:00",
                "sales_rank": 916
            },
            {
                "date": "2025-02-16T06:32:00",
                "sales_rank": 1007
            },
            {
                "date": "2025-02-16T12:28:00",
                "sales_rank": 1197
            },
            {
                "date": "2025-02-16T13:28:00",
                "sales_rank": 1226
            },
            {
                "date": "2025-02-16T17:38:00",
                "sales_rank": 1239
            },
            {
                "date": "2025-02-16T18:46:00",
                "sales_rank": 1274
            },
            {
                "date": "2025-02-16T21:54:00",
                "sales_rank": 1296
            },
            {
                "date": "2025-02-16T22:36:00",
                "sales_rank": 1367
            },
            {
                "date": "2025-02-17T01:56:00",
                "sales_rank": 1440
            },
            {
                "date": "2025-02-17T03:28:00",
                "sales_rank": 1578
            },
            {
                "date": "2025-02-17T06:36:00",
                "sales_rank": 1622
            },
            {
                "date": "2025-02-17T07:56:00",
                "sales_rank": 1650
            },
            {
                "date": "2025-02-17T11:04:00",
                "sales_rank": 811
            },
            {
                "date": "2025-02-17T14:04:00",
                "sales_rank": 897
            },
            {
                "date": "2025-02-17T16:40:00",
                "sales_rank": 925
            },
            {
                "date": "2025-02-17T18:00:00",
                "sales_rank": 959
            },
            {
                "date": "2025-02-17T19:54:00",
                "sales_rank": 1020
            },
            {
                "date": "2025-02-17T23:40:00",
                "sales_rank": 741
            },
            {
                "date": "2025-02-18T02:36:00",
                "sales_rank": 452
            },
            {
                "date": "2025-02-18T09:04:00",
                "sales_rank": 643
            },
            {
                "date": "2025-02-18T13:04:00",
                "sales_rank": 698
            },
            {
                "date": "2025-02-18T18:10:00",
                "sales_rank": 737
            },
            {
                "date": "2025-02-18T21:14:00",
                "sales_rank": 807
            },
            {
                "date": "2025-02-19T00:22:00",
                "sales_rank": 841
            },
            {
                "date": "2025-02-19T03:30:00",
                "sales_rank": 1115
            },
            {
                "date": "2025-02-19T07:40:00",
                "sales_rank": 731
            },
            {
                "date": "2025-02-19T18:42:00",
                "sales_rank": 939
            },
            {
                "date": "2025-02-19T21:32:00",
                "sales_rank": 992
            },
            {
                "date": "2025-02-20T01:20:00",
                "sales_rank": 655
            },
            {
                "date": "2025-02-20T05:24:00",
                "sales_rank": 818
            },
            {
                "date": "2025-02-20T10:30:00",
                "sales_rank": 761
            },
            {
                "date": "2025-02-20T11:36:00",
                "sales_rank": 782
            },
            {
                "date": "2025-02-20T14:14:00",
                "sales_rank": 801
            },
            {
                "date": "2025-02-20T19:42:00",
                "sales_rank": 849
            },
            {
                "date": "2025-02-20T20:54:00",
                "sales_rank": 983
            },
            {
                "date": "2025-02-20T23:18:00",
                "sales_rank": 1078
            },
            {
                "date": "2025-02-21T01:54:00",
                "sales_rank": 1134
            },
            {
                "date": "2025-02-21T05:02:00",
                "sales_rank": 807
            },
            {
                "date": "2025-02-21T08:04:00",
                "sales_rank": 883
            },
            {
                "date": "2025-02-21T11:12:00",
                "sales_rank": 626
            },
            {
                "date": "2025-02-21T14:48:00",
                "sales_rank": 675
            },
            {
                "date": "2025-02-21T21:00:00",
                "sales_rank": 882
            },
            {
                "date": "2025-02-22T08:16:00",
                "sales_rank": 721
            },
            {
                "date": "2025-02-22T11:52:00",
                "sales_rank": 539
            },
            {
                "date": "2025-02-22T16:02:00",
                "sales_rank": 469
            },
            {
                "date": "2025-02-22T17:40:00",
                "sales_rank": 489
            },
            {
                "date": "2025-02-22T19:02:00",
                "sales_rank": 393
            },
            {
                "date": "2025-02-22T21:36:00",
                "sales_rank": 449
            },
            {
                "date": "2025-02-22T23:02:00",
                "sales_rank": 514
            },
            {
                "date": "2025-02-23T00:04:00",
                "sales_rank": 601
            },
            {
                "date": "2025-02-23T02:32:00",
                "sales_rank": 478
            },
            {
                "date": "2025-02-23T05:42:00",
                "sales_rank": 614
            },
            {
                "date": "2025-02-23T10:36:00",
                "sales_rank": 559
            },
            {
                "date": "2025-02-23T15:08:00",
                "sales_rank": 586
            },
            {
                "date": "2025-02-23T18:16:00",
                "sales_rank": 644
            },
            {
                "date": "2025-02-23T22:46:00",
                "sales_rank": 757
            },
            {
                "date": "2025-02-24T01:54:00",
                "sales_rank": 826
            },
            {
                "date": "2025-02-24T05:02:00",
                "sales_rank": 940
            },
            {
                "date": "2025-02-24T08:10:00",
                "sales_rank": 1081
            },
            {
                "date": "2025-02-24T11:20:00",
                "sales_rank": 1090
            },
            {
                "date": "2025-02-24T14:28:00",
                "sales_rank": 1055
            },
            {
                "date": "2025-02-24T17:32:00",
                "sales_rank": 1039
            },
            {
                "date": "2025-02-24T20:44:00",
                "sales_rank": 1081
            },
            {
                "date": "2025-02-25T00:20:00",
                "sales_rank": 1260
            },
            {
                "date": "2025-02-25T02:16:00",
                "sales_rank": 1296
            },
            {
                "date": "2025-02-25T07:04:00",
                "sales_rank": 1496
            },
            {
                "date": "2025-02-25T11:48:00",
                "sales_rank": 925
            },
            {
                "date": "2025-02-25T18:24:00",
                "sales_rank": 1055
            },
            {
                "date": "2025-02-26T02:40:00",
                "sales_rank": 1361
            },
            {
                "date": "2025-02-26T04:24:00",
                "sales_rank": 1397
            },
            {
                "date": "2025-02-26T06:14:00",
                "sales_rank": 1473
            },
            {
                "date": "2025-02-26T09:22:00",
                "sales_rank": 1550
            },
            {
                "date": "2025-02-26T12:30:00",
                "sales_rank": 1556
            },
            {
                "date": "2025-02-26T16:00:00",
                "sales_rank": 1539
            },
            {
                "date": "2025-02-26T21:08:00",
                "sales_rank": 895
            },
            {
                "date": "2025-02-27T01:02:00",
                "sales_rank": 611
            },
            {
                "date": "2025-02-27T02:20:00",
                "sales_rank": 653
            },
            {
                "date": "2025-02-27T03:20:00",
                "sales_rank": 803
            },
            {
                "date": "2025-02-27T09:56:00",
                "sales_rank": 1068
            },
            {
                "date": "2025-02-27T14:00:00",
                "sales_rank": 1105
            },
            {
                "date": "2025-02-27T17:48:00",
                "sales_rank": 1133
            },
            {
                "date": "2025-02-27T20:22:00",
                "sales_rank": 1176
            },
            {
                "date": "2025-02-28T02:32:00",
                "sales_rank": 1434
            },
            {
                "date": "2025-02-28T05:40:00",
                "sales_rank": 1522
            },
            {
                "date": "2025-02-28T11:24:00",
                "sales_rank": 1625
            },
            {
                "date": "2025-02-28T17:36:00",
                "sales_rank": 1634
            },
            {
                "date": "2025-02-28T21:40:00",
                "sales_rank": 1665
            },
            {
                "date": "2025-03-01T02:10:00",
                "sales_rank": 1729
            },
            {
                "date": "2025-03-01T05:18:00",
                "sales_rank": 908
            },
            {
                "date": "2025-03-01T08:26:00",
                "sales_rank": 1106
            },
            {
                "date": "2025-03-01T15:16:00",
                "sales_rank": 1212
            },
            {
                "date": "2025-03-02T03:40:00",
                "sales_rank": 721
            },
            {
                "date": "2025-03-02T07:44:00",
                "sales_rank": 881
            },
            {
                "date": "2025-03-02T10:56:00",
                "sales_rank": 943
            },
            {
                "date": "2025-03-02T14:28:00",
                "sales_rank": 964
            },
            {
                "date": "2025-03-02T18:12:00",
                "sales_rank": 591
            },
            {
                "date": "2025-03-03T03:28:00",
                "sales_rank": 993
            },
            {
                "date": "2025-03-03T05:36:00",
                "sales_rank": 1097
            },
            {
                "date": "2025-03-03T10:40:00",
                "sales_rank": 1260
            },
            {
                "date": "2025-03-03T14:48:00",
                "sales_rank": 1269
            },
            {
                "date": "2025-03-03T17:14:00",
                "sales_rank": 1265
            },
            {
                "date": "2025-03-03T20:22:00",
                "sales_rank": 1322
            },
            {
                "date": "2025-03-03T23:30:00",
                "sales_rank": 1437
            },
            {
                "date": "2025-03-04T03:38:00",
                "sales_rank": 1605
            },
            {
                "date": "2025-03-04T07:20:00",
                "sales_rank": 1643
            },
            {
                "date": "2025-03-04T09:32:00",
                "sales_rank": 1706
            },
            {
                "date": "2025-03-04T11:24:00",
                "sales_rank": 1755
            },
            {
                "date": "2025-03-04T14:20:00",
                "sales_rank": 1747
            },
            {
                "date": "2025-03-04T16:08:00",
                "sales_rank": 763
            },
            {
                "date": "2025-03-04T18:12:00",
                "sales_rank": 823
            },
            {
                "date": "2025-03-04T22:52:00",
                "sales_rank": 602
            },
            {
                "date": "2025-03-05T00:52:00",
                "sales_rank": 758
            },
            {
                "date": "2025-03-05T04:42:00",
                "sales_rank": 850
            },
            {
                "date": "2025-03-05T07:50:00",
                "sales_rank": 1062
            },
            {
                "date": "2025-03-05T10:58:00",
                "sales_rank": 771
            },
            {
                "date": "2025-03-05T14:06:00",
                "sales_rank": 792
            },
            {
                "date": "2025-03-05T17:44:00",
                "sales_rank": 848
            },
            {
                "date": "2025-03-06T00:42:00",
                "sales_rank": 1095
            },
            {
                "date": "2025-03-06T07:00:00",
                "sales_rank": 878
            },
            {
                "date": "2025-03-06T11:34:00",
                "sales_rank": 999
            },
            {
                "date": "2025-03-06T14:42:00",
                "sales_rank": 1040
            },
            {
                "date": "2025-03-06T21:44:00",
                "sales_rank": 1066
            },
            {
                "date": "2025-03-07T00:54:00",
                "sales_rank": 1219
            },
            {
                "date": "2025-03-07T04:02:00",
                "sales_rank": 1273
            },
            {
                "date": "2025-03-07T07:10:00",
                "sales_rank": 1402
            },
            {
                "date": "2025-03-07T10:48:00",
                "sales_rank": 1472
            },
            {
                "date": "2025-03-07T17:16:00",
                "sales_rank": 1459
            },
            {
                "date": "2025-03-08T01:48:00",
                "sales_rank": 1106
            },
            {
                "date": "2025-03-08T11:06:00",
                "sales_rank": 1400
            },
            {
                "date": "2025-03-08T19:08:00",
                "sales_rank": 1410
            },
            {
                "date": "2025-03-08T20:30:00",
                "sales_rank": 1411
            },
            {
                "date": "2025-03-08T23:38:00",
                "sales_rank": 1467
            },
            {
                "date": "2025-03-09T02:46:00",
                "sales_rank": 1552
            },
            {
                "date": "2025-03-10T05:54:00",
                "sales_rank": 1486
            },
            {
                "date": "2025-03-10T10:06:00",
                "sales_rank": 1550
            },
            {
                "date": "2025-03-10T13:14:00",
                "sales_rank": 1573
            },
            {
                "date": "2025-03-10T16:46:00",
                "sales_rank": 1574
            },
            {
                "date": "2025-03-10T18:28:00",
                "sales_rank": 738
            },
            {
                "date": "2025-03-10T21:36:00",
                "sales_rank": 883
            },
            {
                "date": "2025-03-11T02:28:00",
                "sales_rank": 1191
            },
            {
                "date": "2025-03-11T07:28:00",
                "sales_rank": 1355
            },
            {
                "date": "2025-03-11T10:36:00",
                "sales_rank": 1398
            },
            {
                "date": "2025-03-11T13:40:00",
                "sales_rank": 1409
            },
            {
                "date": "2025-03-11T16:46:00",
                "sales_rank": 1440
            },
            {
                "date": "2025-03-11T19:32:00",
                "sales_rank": 1467
            },
            {
                "date": "2025-03-11T22:36:00",
                "sales_rank": 1515
            },
            {
                "date": "2025-03-12T01:44:00",
                "sales_rank": 1602
            },
            {
                "date": "2025-03-12T06:24:00",
                "sales_rank": 1735
            },
            {
                "date": "2025-03-12T13:36:00",
                "sales_rank": 1815
            },
            {
                "date": "2025-03-12T18:32:00",
                "sales_rank": 1838
            },
            {
                "date": "2025-03-12T22:08:00",
                "sales_rank": 1866
            },
            {
                "date": "2025-03-13T05:20:00",
                "sales_rank": 2006
            },
            {
                "date": "2025-03-13T11:02:00",
                "sales_rank": 1120
            },
            {
                "date": "2025-03-13T16:44:00",
                "sales_rank": 1221
            },
            {
                "date": "2025-03-13T20:08:00",
                "sales_rank": 1329
            },
            {
                "date": "2025-03-13T23:48:00",
                "sales_rank": 1487
            },
            {
                "date": "2025-03-14T11:10:00",
                "sales_rank": 1763
            },
            {
                "date": "2025-03-14T15:24:00",
                "sales_rank": 1788
            },
            {
                "date": "2025-03-14T19:26:00",
                "sales_rank": 1825
            },
            {
                "date": "2025-03-14T23:30:00",
                "sales_rank": 1902
            },
            {
                "date": "2025-03-15T01:46:00",
                "sales_rank": 1969
            },
            {
                "date": "2025-03-15T04:54:00",
                "sales_rank": 1992
            },
            {
                "date": "2025-03-15T09:56:00",
                "sales_rank": 2054
            },
            {
                "date": "2025-03-15T23:00:00",
                "sales_rank": 2136
            },
            {
                "date": "2025-03-16T11:04:00",
                "sales_rank": 2267
            },
            {
                "date": "2025-03-16T14:32:00",
                "sales_rank": 2275
            },
            {
                "date": "2025-03-16T18:20:00",
                "sales_rank": 2272
            },
            {
                "date": "2025-03-17T00:52:00",
                "sales_rank": 2326
            },
            {
                "date": "2025-03-17T07:50:00",
                "sales_rank": 2385
            },
            {
                "date": "2025-03-17T10:58:00",
                "sales_rank": 2405
            },
            {
                "date": "2025-03-17T17:46:00",
                "sales_rank": 2410
            },
            {
                "date": "2025-03-17T20:54:00",
                "sales_rank": 2449
            },
            {
                "date": "2025-03-18T00:34:00",
                "sales_rank": 2464
            },
            {
                "date": "2025-03-18T02:52:00",
                "sales_rank": 2483
            },
            {
                "date": "2025-03-18T08:12:00",
                "sales_rank": 2532
            },
            {
                "date": "2025-03-18T17:42:00",
                "sales_rank": 2555
            }
        ]
    }
}