{
    "price_history": [
        {
            "date": "2023-10-07T23:36:00",
            "price": 699.99
        },
        {
            "date": "2023-10-16T05:10:00",
            "price": 959.95
        },
        {
            "date": "2023-10-31T19:12:00",
            "price": 691.95
        },
        {
            "date": "2023-11-01T04:28:00",
            "price": 689.5
        },
        {
            "date": "2023-11-01T17:56:00",
            "price": 691.95
        },
        {
            "date": "2023-11-01T21:40:00",
            "price": 689.5
        },
        {
            "date": "2023-11-05T01:28:00",
            "price": 648.5
        },
        {
            "date": "2023-11-05T04:50:00",
            "price": 649.99
        },
        {
            "date": "2023-11-06T16:48:00",
            "price": 659.99
        },
        {
            "date": "2023-11-06T17:04:00",
            "price": 648.5
        },
        {
            "date": "2023-11-06T18:02:00",
            "price": 659.99
        },
        {
            "date": "2023-11-08T09:12:00",
            "price": 734.95
        },
        {
            "date": "2023-11-08T22:08:00",
            "price": 636.49
        },
        {
            "date": "2023-11-09T06:36:00",
            "price": 734.95
        },
        {
            "date": "2023-11-09T23:44:00",
            "price": 733.9
        },
        {
            "date": "2023-11-10T18:56:00",
            "price": 731.95
        },
        {
            "date": "2023-11-12T01:54:00",
            "price": 999.95
        },
        {
            "date": "2023-11-14T07:24:00",
            "price": 645.0
        },
        {
            "date": "2023-11-14T18:24:00",
            "price": 999.95
        },
        {
            "date": "2023-11-15T00:28:00",
            "price": 648.5
        },
        {
            "date": "2023-11-15T06:00:00",
            "price": 679.99
        },
        {
            "date": "2023-11-15T16:08:00",
            "price": 719.0
        },
        {
            "date": "2023-11-16T01:02:00",
            "price": 719.95
        },
        {
            "date": "2023-11-16T03:00:00",
            "price": 999.95
        },
        {
            "date": "2023-11-16T06:36:00",
            "price": 729.5
        },
        {
            "date": "2023-11-16T14:38:00",
            "price": 999.95
        },
        {
            "date": "2023-11-16T20:08:00",
            "price": 799.99
        },
        {
            "date": "2023-11-17T01:44:00",
            "price": 999.95
        },
        {
            "date": "2023-11-18T01:32:00",
            "price": 729.5
        },
        {
            "date": "2023-11-18T20:22:00",
            "price": 725.0
        },
        {
            "date": "2023-11-19T10:12:00",
            "price": 724.0
        },
        {
            "date": "2023-11-20T11:08:00",
            "price": 723.98
        },
        {
            "date": "2023-11-21T16:10:00",
            "price": 723.0
        },
        {
            "date": "2023-11-22T23:36:00",
            "price": 718.0
        },
        {
            "date": "2023-11-23T06:44:00",
            "price": 699.6
        },
        {
            "date": "2023-11-23T22:44:00",
            "price": 697.6
        },
        {
            "date": "2023-11-24T02:24:00",
            "price": 689.5
        },
        {
            "date": "2023-11-24T20:48:00",
            "price": 723.0
        },
        {
            "date": "2023-12-01T08:32:00",
            "price": 720.95
        },
        {
            "date": "2023-12-02T02:08:00",
            "price": 718.99
        },
        {
            "date": "2023-12-02T06:10:00",
            "price": 713.95
        },
        {
            "date": "2023-12-02T07:36:00",
            "price": 689.5
        },
        {
            "date": "2023-12-03T03:02:00",
            "price": 683.9
        },
        {
            "date": "2023-12-04T23:16:00",
            "price": 680.0
        },
        {
            "date": "2023-12-05T22:40:00",
            "price": 679.0
        },
        {
            "date": "2023-12-07T06:30:00",
            "price": 677.0
        },
        {
            "date": "2023-12-08T16:16:00",
            "price": 675.0
        },
        {
            "date": "2023-12-08T18:20:00",
            "price": 674.0
        },
        {
            "date": "2023-12-08T19:54:00",
            "price": 675.0
        },
        {
            "date": "2023-12-10T03:44:00",
            "price": 674.0
        },
        {
            "date": "2023-12-10T21:28:00",
            "price": 675.0
        },
        {
            "date": "2023-12-12T01:34:00",
            "price": 676.0
        },
        {
            "date": "2023-12-14T04:56:00",
            "price": 675.0
        },
        {
            "date": "2023-12-14T17:56:00",
            "price": 689.94
        },
        {
            "date": "2023-12-14T22:04:00",
            "price": 675.99
        },
        {
            "date": "2023-12-15T05:12:00",
            "price": 676.0
        },
        {
            "date": "2023-12-15T17:54:00",
            "price": 669.24
        },
        {
            "date": "2023-12-15T22:48:00",
            "price": 689.95
        },
        {
            "date": "2023-12-16T02:06:00",
            "price": 689.0
        },
        {
            "date": "2023-12-16T17:08:00",
            "price": 689.95
        },
        {
            "date": "2023-12-18T17:00:00",
            "price": 680.7
        },
        {
            "date": "2023-12-18T23:20:00",
            "price": 688.95
        },
        {
            "date": "2023-12-19T02:20:00",
            "price": 799.5
        },
        {
            "date": "2023-12-20T02:08:00",
            "price": 688.0
        },
        {
            "date": "2023-12-21T18:56:00",
            "price": 894.95
        },
        {
            "date": "2023-12-22T20:40:00",
            "price": 799.5
        },
        {
            "date": "2023-12-23T14:08:00",
            "price": 687.0
        },
        {
            "date": "2023-12-24T08:22:00",
            "price": 688.0
        },
        {
            "date": "2023-12-28T17:58:00",
            "price": 680.0
        },
        {
            "date": "2024-01-04T09:00:00",
            "price": 679.99
        },
        {
            "date": "2024-01-08T16:56:00",
            "price": 678.94
        },
        {
            "date": "2024-01-13T00:44:00",
            "price": 668.45
        },
        {
            "date": "2024-01-16T19:50:00",
            "price": 658.95
        },
        {
            "date": "2024-01-20T00:20:00",
            "price": 647.95
        },
        {
            "date": "2024-01-20T22:10:00",
            "price": 641.0
        },
        {
            "date": "2024-01-21T06:16:00",
            "price": 639.95
        },
        {
            "date": "2024-01-22T19:32:00",
            "price": 628.95
        },
        {
            "date": "2024-01-24T03:28:00",
            "price": 621.45
        },
        {
            "date": "2024-01-26T02:34:00",
            "price": 612.69
        },
        {
            "date": "2024-01-28T00:02:00",
            "price": 598.45
        },
        {
            "date": "2024-02-02T19:36:00",
            "price": 629.0
        },
        {
            "date": "2024-02-04T19:38:00",
            "price": 598.45
        },
        {
            "date": "2024-02-07T22:58:00",
            "price": 598.43
        },
        {
            "date": "2024-02-08T10:00:00",
            "price": 598.41
        },
        {
            "date": "2024-02-08T16:58:00",
            "price": 585.0
        },
        {
            "date": "2024-02-09T01:32:00",
            "price": 583.95
        },
        {
            "date": "2024-02-14T00:16:00",
            "price": 588.95
        },
        {
            "date": "2024-02-14T15:44:00",
            "price": 590.0
        },
        {
            "date": "2024-02-14T21:50:00",
            "price": 589.5
        },
        {
            "date": "2024-02-15T22:16:00",
            "price": 589.0
        },
        {
            "date": "2024-02-16T05:36:00",
            "price": 583.95
        },
        {
            "date": "2024-02-18T02:28:00",
            "price": 599.49
        },
        {
            "date": "2024-02-19T18:48:00",
            "price": 678.99
        },
        {
            "date": "2024-02-20T03:04:00",
            "price": 669.0
        },
        {
            "date": "2024-02-20T21:58:00",
            "price": 678.99
        },
        {
            "date": "2024-02-21T04:14:00",
            "price": 679.99
        },
        {
            "date": "2024-02-23T01:04:00",
            "price": 650.0
        },
        {
            "date": "2024-02-23T20:40:00",
            "price": 589.5
        },
        {
            "date": "2024-02-29T00:54:00",
            "price": 689.95
        },
        {
            "date": "2024-02-29T22:44:00",
            "price": 649.95
        },
        {
            "date": "2024-03-02T03:06:00",
            "price": 649.0
        },
        {
            "date": "2024-03-05T05:40:00",
            "price": 649.0
        },
        {
            "date": "2024-03-06T18:16:00",
            "price": 679.99
        },
        {
            "date": "2024-03-07T03:12:00",
            "price": 644.5
        },
        {
            "date": "2024-03-07T12:38:00",
            "price": 678.99
        },
        {
            "date": "2024-03-09T00:48:00",
            "price": 638.31
        },
        {
            "date": "2024-03-09T04:48:00",
            "price": 678.99
        },
        {
            "date": "2024-03-10T22:06:00",
            "price": 799.5
        },
        {
            "date": "2024-03-12T02:32:00",
            "price": 653.74
        },
        {
            "date": "2024-03-12T07:48:00",
            "price": 799.5
        },
        {
            "date": "2024-03-12T18:16:00",
            "price": 729.5
        },
        {
            "date": "2024-03-12T19:20:00",
            "price": 799.5
        },
        {
            "date": "2024-03-12T23:08:00",
            "price": 614.0
        },
        {
            "date": "2024-03-13T20:56:00",
            "price": 799.5
        },
        {
            "date": "2024-03-14T00:56:00",
            "price": 763.0
        },
        {
            "date": "2024-03-14T06:06:00",
            "price": 756.99
        },
        {
            "date": "2024-03-14T15:22:00",
            "price": 713.0
        },
        {
            "date": "2024-03-14T18:32:00",
            "price": 697.0
        },
        {
            "date": "2024-03-15T04:54:00",
            "price": 696.0
        },
        {
            "date": "2024-03-15T10:02:00",
            "price": 690.0
        },
        {
            "date": "2024-03-15T18:42:00",
            "price": 696.0
        },
        {
            "date": "2024-03-15T21:50:00",
            "price": 625.45
        },
        {
            "date": "2024-03-16T00:56:00",
            "price": 615.55
        },
        {
            "date": "2024-03-16T18:30:00",
            "price": 604.66
        },
        {
            "date": "2024-03-16T21:20:00",
            "price": 597.5
        },
        {
            "date": "2024-03-17T00:28:00",
            "price": 596.5
        },
        {
            "date": "2024-03-17T19:28:00",
            "price": 594.5
        },
        {
            "date": "2024-03-18T05:00:00",
            "price": 587.5
        },
        {
            "date": "2024-03-18T13:16:00",
            "price": 615.55
        },
        {
            "date": "2024-03-18T18:02:00",
            "price": 603.55
        },
        {
            "date": "2024-03-18T21:10:00",
            "price": 583.0
        },
        {
            "date": "2024-03-19T17:44:00",
            "price": 571.0
        },
        {
            "date": "2024-03-19T19:04:00",
            "price": 569.0
        },
        {
            "date": "2024-03-19T22:10:00",
            "price": 567.99
        },
        {
            "date": "2024-03-20T06:04:00",
            "price": 567.0
        },
        {
            "date": "2024-03-20T22:04:00",
            "price": 565.94
        },
        {
            "date": "2024-03-21T00:26:00",
            "price": 550.69
        },
        {
            "date": "2024-03-21T03:34:00",
            "price": 547.95
        },
        {
            "date": "2024-03-21T18:36:00",
            "price": 536.8
        },
        {
            "date": "2024-03-22T18:58:00",
            "price": 534.8
        },
        {
            "date": "2024-03-23T13:10:00",
            "price": 530.7
        },
        {
            "date": "2024-03-23T16:18:00",
            "price": 528.45
        },
        {
            "date": "2024-03-27T01:24:00",
            "price": 529.5
        },
        {
            "date": "2024-03-28T18:42:00",
            "price": 542.0
        },
        {
            "date": "2024-03-28T23:26:00",
            "price": 539.0
        },
        {
            "date": "2024-03-29T16:46:00",
            "price": 541.0
        },
        {
            "date": "2024-03-30T01:22:00",
            "price": 549.88
        },
        {
            "date": "2024-03-30T04:30:00",
            "price": 559.88
        },
        {
            "date": "2024-03-30T15:44:00",
            "price": 569.99
        },
        {
            "date": "2024-04-02T01:06:00",
            "price": 568.44
        },
        {
            "date": "2024-04-03T04:14:00",
            "price": 562.34
        },
        {
            "date": "2024-04-03T06:08:00",
            "price": 554.95
        },
        {
            "date": "2024-04-04T18:50:00",
            "price": 549.99
        },
        {
            "date": "2024-04-05T02:20:00",
            "price": 544.0
        },
        {
            "date": "2024-04-05T07:32:00",
            "price": 543.0
        },
        {
            "date": "2024-04-05T16:10:00",
            "price": 544.0
        },
        {
            "date": "2024-04-05T23:34:00",
            "price": 554.0
        },
        {
            "date": "2024-04-06T21:20:00",
            "price": 552.95
        },
        {
            "date": "2024-04-07T07:50:00",
            "price": 544.25
        },
        {
            "date": "2024-04-08T15:40:00",
            "price": 552.0
        },
        {
            "date": "2024-04-08T19:00:00",
            "price": 544.25
        },
        {
            "date": "2024-04-09T14:42:00",
            "price": 544.5
        },
        {
            "date": "2024-04-10T00:06:00",
            "price": 607.46
        },
        {
            "date": "2024-04-10T13:56:00",
            "price": 636.05
        },
        {
            "date": "2024-04-10T15:52:00",
            "price": 674.67
        },
        {
            "date": "2024-04-10T18:14:00",
            "price": 569.99
        },
        {
            "date": "2024-04-10T21:22:00",
            "price": 636.05
        },
        {
            "date": "2024-04-10T23:44:00",
            "price": 639.97
        },
        {
            "date": "2024-04-11T17:20:00",
            "price": 639.99
        },
        {
            "date": "2024-04-11T20:26:00",
            "price": 744.69
        },
        {
            "date": "2024-04-12T00:04:00",
            "price": 830.97
        },
        {
            "date": "2024-04-12T05:12:00",
            "price": 821.29
        },
        {
            "date": "2024-04-12T20:38:00",
            "price": 569.99
        },
        {
            "date": "2024-04-13T05:58:00",
            "price": 599.99
        },
        {
            "date": "2024-04-14T06:20:00",
            "price": 609.5
        },
        {
            "date": "2024-04-15T23:16:00",
            "price": 544.25
        },
        {
            "date": "2024-04-16T02:46:00",
            "price": 609.5
        },
        {
            "date": "2024-04-16T10:02:00",
            "price": 544.25
        },
        {
            "date": "2024-04-16T16:18:00",
            "price": 609.5
        },
        {
            "date": "2024-04-16T21:52:00",
            "price": 550.0
        },
        {
            "date": "2024-04-17T21:26:00",
            "price": 609.5
        },
        {
            "date": "2024-04-19T00:48:00",
            "price": 602.5
        },
        {
            "date": "2024-04-19T14:42:00",
            "price": 604.5
        },
        {
            "date": "2024-04-19T16:40:00",
            "price": 599.99
        },
        {
            "date": "2024-04-19T21:12:00",
            "price": 589.99
        },
        {
            "date": "2024-04-20T07:32:00",
            "price": 599.99
        },
        {
            "date": "2024-04-22T23:28:00",
            "price": 550.0
        },
        {
            "date": "2024-04-23T19:32:00",
            "price": 599.99
        },
        {
            "date": "2024-04-24T18:14:00",
            "price": 544.25
        },
        {
            "date": "2024-04-24T23:24:00",
            "price": 599.99
        },
        {
            "date": "2024-04-26T15:44:00",
            "price": 599.0
        },
        {
            "date": "2024-04-27T05:00:00",
            "price": 593.0
        },
        {
            "date": "2024-04-27T10:24:00",
            "price": 589.0
        },
        {
            "date": "2024-04-28T18:20:00",
            "price": 588.0
        },
        {
            "date": "2024-04-29T06:32:00",
            "price": 589.0
        },
        {
            "date": "2024-04-29T23:46:00",
            "price": 550.0
        },
        {
            "date": "2024-04-30T14:16:00",
            "price": 569.0
        },
        {
            "date": "2024-04-30T23:38:00",
            "price": 589.0
        },
        {
            "date": "2024-05-02T18:34:00",
            "price": 544.25
        },
        {
            "date": "2024-05-03T00:50:00",
            "price": 544.23
        },
        {
            "date": "2024-05-03T03:58:00",
            "price": 535.67
        },
        {
            "date": "2024-05-03T07:06:00",
            "price": 588.98
        },
        {
            "date": "2024-05-03T20:48:00",
            "price": 524.99
        },
        {
            "date": "2024-05-04T03:24:00",
            "price": 509.96
        },
        {
            "date": "2024-05-04T18:24:00",
            "price": 558.6
        },
        {
            "date": "2024-05-05T08:26:00",
            "price": 558.58
        },
        {
            "date": "2024-05-06T02:08:00",
            "price": 588.98
        },
        {
            "date": "2024-05-06T05:14:00",
            "price": 588.9
        },
        {
            "date": "2024-05-07T02:42:00",
            "price": 583.15
        },
        {
            "date": "2024-05-07T07:52:00",
            "price": 559.45
        },
        {
            "date": "2024-05-07T16:28:00",
            "price": 563.9
        },
        {
            "date": "2024-05-07T22:18:00",
            "price": 564.0
        },
        {
            "date": "2024-05-10T17:46:00",
            "price": 563.96
        },
        {
            "date": "2024-05-10T19:48:00",
            "price": 562.46
        },
        {
            "date": "2024-05-10T23:00:00",
            "price": 559.4
        },
        {
            "date": "2024-05-11T03:08:00",
            "price": 552.96
        },
        {
            "date": "2024-05-12T04:34:00",
            "price": 552.98
        },
        {
            "date": "2024-05-13T06:18:00",
            "price": 584.0
        },
        {
            "date": "2024-05-13T09:26:00",
            "price": 579.0
        },
        {
            "date": "2024-05-13T15:02:00",
            "price": 565.68
        },
        {
            "date": "2024-05-13T22:10:00",
            "price": 584.0
        },
        {
            "date": "2024-05-15T01:34:00",
            "price": 577.0
        },
        {
            "date": "2024-05-15T04:42:00",
            "price": 571.0
        },
        {
            "date": "2024-05-15T07:50:00",
            "price": 567.0
        },
        {
            "date": "2024-05-15T11:12:00",
            "price": 569.0
        },
        {
            "date": "2024-05-16T02:36:00",
            "price": 567.0
        },
        {
            "date": "2024-05-17T03:20:00",
            "price": 566.96
        },
        {
            "date": "2024-05-17T11:48:00",
            "price": 567.0
        },
        {
            "date": "2024-05-21T02:26:00",
            "price": 569.0
        },
        {
            "date": "2024-05-31T02:42:00",
            "price": 584.0
        },
        {
            "date": "2024-05-31T22:56:00",
            "price": 580.0
        },
        {
            "date": "2024-06-01T02:04:00",
            "price": 574.0
        },
        {
            "date": "2024-06-01T17:12:00",
            "price": 572.0
        },
        {
            "date": "2024-06-02T00:06:00",
            "price": 582.0
        },
        {
            "date": "2024-06-02T08:34:00",
            "price": 584.0
        },
        {
            "date": "2024-06-04T19:46:00",
            "price": 579.99
        },
        {
            "date": "2024-06-05T04:06:00",
            "price": 584.0
        },
        {
            "date": "2024-06-07T17:56:00",
            "price": 583.0
        },
        {
            "date": "2024-06-07T21:52:00",
            "price": 584.0
        },
        {
            "date": "2024-06-09T23:48:00",
            "price": 609.99
        },
        {
            "date": "2024-06-10T07:20:00",
            "price": 584.0
        },
        {
            "date": "2024-06-11T19:24:00",
            "price": 582.0
        },
        {
            "date": "2024-06-12T03:30:00",
            "price": 569.78
        },
        {
            "date": "2024-06-12T06:38:00",
            "price": 564.35
        },
        {
            "date": "2024-06-13T02:50:00",
            "price": 584.0
        },
        {
            "date": "2024-06-14T16:20:00",
            "price": 580.0
        },
        {
            "date": "2024-06-14T18:08:00",
            "price": 570.0
        },
        {
            "date": "2024-06-14T20:52:00",
            "price": 580.0
        },
        {
            "date": "2024-06-19T00:38:00",
            "price": 559.96
        },
        {
            "date": "2024-06-19T15:16:00",
            "price": 580.0
        },
        {
            "date": "2024-06-22T02:20:00",
            "price": 571.74
        },
        {
            "date": "2024-06-22T19:30:00",
            "price": 580.0
        },
        {
            "date": "2024-06-23T09:10:00",
            "price": 584.0
        },
        {
            "date": "2024-06-23T23:16:00",
            "price": 580.0
        },
        {
            "date": "2024-06-24T02:22:00",
            "price": 583.96
        },
        {
            "date": "2024-06-24T19:52:00",
            "price": 559.96
        },
        {
            "date": "2024-06-25T16:24:00",
            "price": 584.0
        },
        {
            "date": "2024-06-26T18:22:00",
            "price": 525.0
        },
        {
            "date": "2024-06-26T21:30:00",
            "price": 584.0
        },
        {
            "date": "2024-06-29T00:56:00",
            "price": 582.0
        },
        {
            "date": "2024-07-02T05:04:00",
            "price": 580.0
        },
        {
            "date": "2024-07-02T16:48:00",
            "price": 582.0
        },
        {
            "date": "2024-07-03T14:36:00",
            "price": 669.99
        },
        {
            "date": "2024-07-03T19:48:00",
            "price": 581.96
        },
        {
            "date": "2024-07-08T17:32:00",
            "price": 581.0
        },
        {
            "date": "2024-07-08T23:20:00",
            "price": 580.96
        },
        {
            "date": "2024-07-10T22:10:00",
            "price": 586.29
        },
        {
            "date": "2024-07-11T02:16:00",
            "price": 586.27
        },
        {
            "date": "2024-07-11T03:36:00",
            "price": 586.07
        },
        {
            "date": "2024-07-11T08:28:00",
            "price": 585.47
        },
        {
            "date": "2024-07-11T13:20:00",
            "price": 584.77
        },
        {
            "date": "2024-07-11T14:06:00",
            "price": 584.65
        },
        {
            "date": "2024-07-11T18:08:00",
            "price": 550.0
        },
        {
            "date": "2024-07-12T00:00:00",
            "price": 572.04
        },
        {
            "date": "2024-07-14T18:12:00",
            "price": 571.04
        },
        {
            "date": "2024-07-15T17:12:00",
            "price": 588.0
        },
        {
            "date": "2024-07-16T16:26:00",
            "price": 589.0
        },
        {
            "date": "2024-07-18T18:40:00",
            "price": 588.0
        },
        {
            "date": "2024-07-18T20:08:00",
            "price": 582.0
        },
        {
            "date": "2024-07-19T15:08:00",
            "price": 581.0
        },
        {
            "date": "2024-07-21T17:40:00",
            "price": 582.0
        },
        {
            "date": "2024-07-23T18:40:00",
            "price": 589.0
        },
        {
            "date": "2024-07-30T17:40:00",
            "price": 588.0
        },
        {
            "date": "2024-07-30T20:08:00",
            "price": 589.0
        },
        {
            "date": "2024-07-31T00:04:00",
            "price": 588.0
        },
        {
            "date": "2024-07-31T03:32:00",
            "price": 587.0
        },
        {
            "date": "2024-07-31T22:04:00",
            "price": 588.0
        },
        {
            "date": "2024-08-01T22:20:00",
            "price": 587.99
        },
        {
            "date": "2024-08-02T03:58:00",
            "price": 589.0
        },
        {
            "date": "2024-08-02T07:06:00",
            "price": 588.0
        },
        {
            "date": "2024-08-02T10:14:00",
            "price": 589.0
        },
        {
            "date": "2024-08-05T18:44:00",
            "price": 639.99
        },
        {
            "date": "2024-08-06T22:02:00",
            "price": 587.0
        },
        {
            "date": "2024-08-07T01:10:00",
            "price": 588.0
        },
        {
            "date": "2024-08-07T08:08:00",
            "price": 639.99
        },
        {
            "date": "2024-08-07T22:34:00",
            "price": 599.99
        },
        {
            "date": "2024-08-10T00:38:00",
            "price": 589.08
        },
        {
            "date": "2024-08-10T03:44:00",
            "price": 587.96
        },
        {
            "date": "2024-08-10T04:56:00",
            "price": 587.89
        },
        {
            "date": "2024-08-10T08:32:00",
            "price": 587.59
        },
        {
            "date": "2024-08-10T21:20:00",
            "price": 603.43
        },
        {
            "date": "2024-08-11T17:24:00",
            "price": 599.99
        },
        {
            "date": "2024-08-12T06:20:00",
            "price": 587.61
        },
        {
            "date": "2024-08-12T15:48:00",
            "price": 587.61
        },
        {
            "date": "2024-08-13T03:32:00",
            "price": 603.43
        },
        {
            "date": "2024-08-13T19:32:00",
            "price": 639.0
        },
        {
            "date": "2024-08-14T00:04:00",
            "price": 570.74
        },
        {
            "date": "2024-08-14T07:16:00",
            "price": 639.0
        },
        {
            "date": "2024-08-16T03:42:00",
            "price": 631.23
        },
        {
            "date": "2024-08-16T11:36:00",
            "price": 627.1
        },
        {
            "date": "2024-08-16T20:56:00",
            "price": 549.0
        },
        {
            "date": "2024-08-17T07:06:00",
            "price": 599.99
        },
        {
            "date": "2024-08-21T19:02:00",
            "price": 629.5
        },
        {
            "date": "2024-08-23T06:32:00",
            "price": 609.0
        },
        {
            "date": "2024-08-23T16:44:00",
            "price": 600.74
        },
        {
            "date": "2024-08-23T20:08:00",
            "price": 598.64
        },
        {
            "date": "2024-08-23T23:58:00",
            "price": 585.99
        },
        {
            "date": "2024-08-24T02:48:00",
            "price": 582.72
        },
        {
            "date": "2024-08-24T07:04:00",
            "price": 582.84
        },
        {
            "date": "2024-08-24T18:02:00",
            "price": 609.0
        },
        {
            "date": "2024-08-25T04:00:00",
            "price": 619.99
        },
        {
            "date": "2024-08-25T16:04:00",
            "price": 629.5
        },
        {
            "date": "2024-08-25T17:52:00",
            "price": 599.74
        },
        {
            "date": "2024-08-26T20:00:00",
            "price": 579.99
        },
        {
            "date": "2024-08-27T06:32:00",
            "price": 579.63
        },
        {
            "date": "2024-08-27T08:44:00",
            "price": 579.37
        },
        {
            "date": "2024-08-27T11:50:00",
            "price": 579.03
        },
        {
            "date": "2024-08-27T16:44:00",
            "price": 578.53
        },
        {
            "date": "2024-08-27T22:42:00",
            "price": 577.85
        },
        {
            "date": "2024-08-28T01:50:00",
            "price": 577.51
        },
        {
            "date": "2024-08-28T04:58:00",
            "price": 577.19
        },
        {
            "date": "2024-08-28T08:06:00",
            "price": 577.07
        },
        {
            "date": "2024-08-28T23:12:00",
            "price": 589.0
        },
        {
            "date": "2024-09-06T23:54:00",
            "price": 587.0
        },
        {
            "date": "2024-09-07T05:02:00",
            "price": 589.0
        },
        {
            "date": "2024-09-10T21:28:00",
            "price": 587.0
        },
        {
            "date": "2024-09-11T18:20:00",
            "price": 581.75
        },
        {
            "date": "2024-09-12T00:32:00",
            "price": 589.0
        },
        {
            "date": "2024-09-14T01:00:00",
            "price": 577.76
        },
        {
            "date": "2024-09-16T23:16:00",
            "price": 577.0
        },
        {
            "date": "2024-09-17T00:58:00",
            "price": 575.94
        },
        {
            "date": "2024-09-18T00:04:00",
            "price": 575.65
        },
        {
            "date": "2024-09-18T04:56:00",
            "price": 573.95
        },
        {
            "date": "2024-09-18T13:16:00",
            "price": 573.9
        },
        {
            "date": "2024-09-18T16:36:00",
            "price": 573.45
        },
        {
            "date": "2024-09-18T22:44:00",
            "price": 572.95
        },
        {
            "date": "2024-09-19T01:56:00",
            "price": 572.75
        },
        {
            "date": "2024-09-19T14:20:00",
            "price": 572.55
        },
        {
            "date": "2024-09-19T17:04:00",
            "price": 572.45
        },
        {
            "date": "2024-09-20T05:34:00",
            "price": 571.93
        },
        {
            "date": "2024-09-20T08:56:00",
            "price": 571.38
        },
        {
            "date": "2024-09-20T13:02:00",
            "price": 570.54
        },
        {
            "date": "2024-09-20T14:06:00",
            "price": 570.38
        },
        {
            "date": "2024-09-20T17:40:00",
            "price": 569.76
        },
        {
            "date": "2024-09-20T20:46:00",
            "price": 568.36
        },
        {
            "date": "2024-09-21T01:26:00",
            "price": 567.45
        },
        {
            "date": "2024-09-21T07:38:00",
            "price": 566.26
        },
        {
            "date": "2024-09-21T12:48:00",
            "price": 565.31
        },
        {
            "date": "2024-09-21T19:12:00",
            "price": 560.08
        },
        {
            "date": "2024-09-21T23:38:00",
            "price": 559.23
        },
        {
            "date": "2024-09-22T03:48:00",
            "price": 558.54
        },
        {
            "date": "2024-09-22T05:48:00",
            "price": 558.26
        },
        {
            "date": "2024-09-22T08:18:00",
            "price": 557.98
        },
        {
            "date": "2024-09-22T12:04:00",
            "price": 557.56
        },
        {
            "date": "2024-09-22T14:52:00",
            "price": 557.1
        },
        {
            "date": "2024-09-22T18:00:00",
            "price": 556.46
        },
        {
            "date": "2024-09-22T21:08:00",
            "price": 555.8
        },
        {
            "date": "2024-09-22T23:56:00",
            "price": 555.2
        },
        {
            "date": "2024-09-23T03:04:00",
            "price": 554.7
        },
        {
            "date": "2024-09-23T17:22:00",
            "price": 548.95
        },
        {
            "date": "2024-09-23T20:30:00",
            "price": 546.95
        },
        {
            "date": "2024-09-28T02:56:00",
            "price": 559.44
        },
        {
            "date": "2024-09-28T06:04:00",
            "price": 558.76
        },
        {
            "date": "2024-09-28T07:12:00",
            "price": 558.51
        },
        {
            "date": "2024-09-28T09:04:00",
            "price": 557.99
        },
        {
            "date": "2024-09-28T15:08:00",
            "price": 556.63
        },
        {
            "date": "2024-09-28T22:36:00",
            "price": 554.93
        },
        {
            "date": "2024-09-29T01:44:00",
            "price": 554.54
        },
        {
            "date": "2024-09-29T18:10:00",
            "price": 565.95
        },
        {
            "date": "2024-09-30T21:04:00",
            "price": 565.9
        },
        {
            "date": "2024-10-01T07:26:00",
            "price": 563.94
        },
        {
            "date": "2024-10-01T17:08:00",
            "price": 559.94
        },
        {
            "date": "2024-10-05T04:16:00",
            "price": 558.89
        },
        {
            "date": "2024-10-08T00:20:00",
            "price": 558.39
        },
        {
            "date": "2024-10-08T03:26:00",
            "price": 557.66
        },
        {
            "date": "2024-10-08T06:46:00",
            "price": 556.82
        },
        {
            "date": "2024-10-08T13:46:00",
            "price": 555.2
        },
        {
            "date": "2024-10-08T16:54:00",
            "price": 554.45
        },
        {
            "date": "2024-10-16T05:22:00",
            "price": 553.35
        },
        {
            "date": "2024-10-16T10:32:00",
            "price": 552.33
        },
        {
            "date": "2024-10-16T13:58:00",
            "price": 551.69
        },
        {
            "date": "2024-10-16T17:48:00",
            "price": 550.88
        },
        {
            "date": "2024-10-17T01:12:00",
            "price": 549.47
        },
        {
            "date": "2024-10-17T03:56:00",
            "price": 548.91
        },
        {
            "date": "2024-10-17T05:48:00",
            "price": 548.53
        },
        {
            "date": "2024-10-17T08:54:00",
            "price": 547.95
        },
        {
            "date": "2024-10-17T12:02:00",
            "price": 547.34
        },
        {
            "date": "2024-10-17T13:40:00",
            "price": 547.02
        },
        {
            "date": "2024-10-17T17:28:00",
            "price": 546.42
        },
        {
            "date": "2024-10-18T00:42:00",
            "price": 544.99
        },
        {
            "date": "2024-10-18T06:12:00",
            "price": 544.57
        },
        {
            "date": "2024-10-19T03:56:00",
            "price": 544.04
        },
        {
            "date": "2024-10-19T08:16:00",
            "price": 543.08
        },
        {
            "date": "2024-10-19T14:26:00",
            "price": 541.8
        },
        {
            "date": "2024-10-19T18:32:00",
            "price": 540.98
        },
        {
            "date": "2024-10-19T21:40:00",
            "price": 530.84
        },
        {
            "date": "2024-10-20T00:36:00",
            "price": 530.34
        },
        {
            "date": "2024-10-20T04:56:00",
            "price": 529.82
        },
        {
            "date": "2024-10-20T11:06:00",
            "price": 529.0
        },
        {
            "date": "2024-10-20T15:00:00",
            "price": 528.48
        },
        {
            "date": "2024-10-20T18:20:00",
            "price": 527.73
        },
        {
            "date": "2024-10-21T02:46:00",
            "price": 526.03
        },
        {
            "date": "2024-10-21T07:26:00",
            "price": 525.21
        },
        {
            "date": "2024-10-21T10:34:00",
            "price": 524.66
        },
        {
            "date": "2024-10-21T12:24:00",
            "price": 524.37
        },
        {
            "date": "2024-10-21T16:12:00",
            "price": 523.37
        },
        {
            "date": "2024-10-22T20:32:00",
            "price": 513.95
        },
        {
            "date": "2024-10-22T23:40:00",
            "price": 504.14
        },
        {
            "date": "2024-10-23T10:04:00",
            "price": 531.61
        },
        {
            "date": "2024-10-23T16:14:00",
            "price": 542.3
        },
        {
            "date": "2024-10-23T20:48:00",
            "price": 543.3
        },
        {
            "date": "2024-10-24T22:52:00",
            "price": 483.99
        },
        {
            "date": "2024-10-31T03:52:00",
            "price": 483.94
        },
        {
            "date": "2024-10-31T18:48:00",
            "price": 483.99
        },
        {
            "date": "2024-11-05T01:08:00",
            "price": 480.95
        },
        {
            "date": "2024-11-05T16:14:00",
            "price": 482.94
        },
        {
            "date": "2024-11-05T22:50:00",
            "price": 478.43
        },
        {
            "date": "2024-11-06T05:40:00",
            "price": 478.11
        },
        {
            "date": "2024-11-09T05:58:00",
            "price": 473.95
        },
        {
            "date": "2024-11-11T17:50:00",
            "price": 535.0
        },
        {
            "date": "2024-11-12T04:56:00",
            "price": 599.96
        },
        {
            "date": "2024-11-12T22:24:00",
            "price": 534.95
        },
        {
            "date": "2024-11-13T21:44:00",
            "price": 532.95
        },
        {
            "date": "2024-11-14T06:36:00",
            "price": 499.0
        },
        {
            "date": "2024-11-18T19:04:00",
            "price": 499.99
        },
        {
            "date": "2024-11-19T05:28:00",
            "price": 499.49
        },
        {
            "date": "2024-11-19T17:58:00",
            "price": 499.99
        },
        {
            "date": "2024-11-20T02:16:00",
            "price": 499.49
        },
        {
            "date": "2024-11-20T05:24:00",
            "price": 499.99
        },
        {
            "date": "2024-11-20T17:02:00",
            "price": 509.44
        },
        {
            "date": "2024-11-21T00:16:00",
            "price": 509.95
        },
        {
            "date": "2024-11-21T07:44:00",
            "price": 509.44
        },
        {
            "date": "2024-11-21T21:42:00",
            "price": 541.1
        },
        {
            "date": "2024-11-22T05:08:00",
            "price": 506.75
        },
        {
            "date": "2024-11-22T08:16:00",
            "price": 503.71
        },
        {
            "date": "2024-11-22T11:36:00",
            "price": 500.98
        },
        {
            "date": "2024-11-22T17:46:00",
            "price": 541.11
        },
        {
            "date": "2024-11-23T03:56:00",
            "price": 541.05
        },
        {
            "date": "2024-11-23T05:32:00",
            "price": 540.93
        },
        {
            "date": "2024-11-23T09:16:00",
            "price": 540.53
        },
        {
            "date": "2024-11-23T17:32:00",
            "price": 539.57
        },
        {
            "date": "2024-11-24T01:46:00",
            "price": 499.5
        },
        {
            "date": "2024-11-24T05:00:00",
            "price": 535.75
        },
        {
            "date": "2024-11-24T18:30:00",
            "price": 535.78
        },
        {
            "date": "2024-11-24T21:38:00",
            "price": 535.79
        },
        {
            "date": "2024-11-25T02:34:00",
            "price": 535.82
        },
        {
            "date": "2024-11-25T10:50:00",
            "price": 549.99
        },
        {
            "date": "2024-11-26T02:20:00",
            "price": 548.99
        },
        {
            "date": "2024-11-26T03:56:00",
            "price": 524.5
        },
        {
            "date": "2024-11-26T23:58:00",
            "price": 504.2
        },
        {
            "date": "2024-11-28T04:18:00",
            "price": 498.0
        },
        {
            "date": "2024-11-29T10:24:00",
            "price": 504.8
        },
        {
            "date": "2024-11-30T18:28:00",
            "price": 597.99
        },
        {
            "date": "2024-12-01T00:38:00",
            "price": 599.94
        },
        {
            "date": "2024-12-03T01:28:00",
            "price": 529.15
        },
        {
            "date": "2024-12-03T12:36:00",
            "price": 516.9
        },
        {
            "date": "2024-12-03T14:28:00",
            "price": 505.25
        },
        {
            "date": "2024-12-03T17:44:00",
            "price": 505.3
        },
        {
            "date": "2024-12-03T23:32:00",
            "price": 579.91
        },
        {
            "date": "2024-12-04T02:40:00",
            "price": 579.84
        },
        {
            "date": "2024-12-04T06:08:00",
            "price": 579.5
        },
        {
            "date": "2024-12-04T12:56:00",
            "price": 578.68
        },
        {
            "date": "2024-12-04T16:04:00",
            "price": 578.28
        },
        {
            "date": "2024-12-04T20:26:00",
            "price": 577.8
        },
        {
            "date": "2024-12-05T04:42:00",
            "price": 576.6
        },
        {
            "date": "2024-12-05T05:52:00",
            "price": 576.46
        },
        {
            "date": "2024-12-05T09:00:00",
            "price": 576.08
        },
        {
            "date": "2024-12-05T10:28:00",
            "price": 575.83
        },
        {
            "date": "2024-12-05T14:44:00",
            "price": 575.04
        },
        {
            "date": "2024-12-05T21:42:00",
            "price": 499.95
        },
        {
            "date": "2024-12-07T01:52:00",
            "price": 539.13
        },
        {
            "date": "2024-12-07T10:08:00",
            "price": 539.14
        },
        {
            "date": "2024-12-08T08:04:00",
            "price": 539.15
        },
        {
            "date": "2024-12-08T16:06:00",
            "price": 539.17
        },
        {
            "date": "2024-12-10T00:56:00",
            "price": 604.46
        },
        {
            "date": "2024-12-10T04:04:00",
            "price": 604.35
        },
        {
            "date": "2024-12-10T05:06:00",
            "price": 604.27
        },
        {
            "date": "2024-12-10T08:14:00",
            "price": 603.89
        },
        {
            "date": "2024-12-10T11:22:00",
            "price": 603.53
        },
        {
            "date": "2024-12-10T17:36:00",
            "price": 602.99
        },
        {
            "date": "2024-12-11T00:28:00",
            "price": 602.19
        },
        {
            "date": "2024-12-11T00:44:00",
            "price": 602.15
        },
        {
            "date": "2024-12-11T03:50:00",
            "price": 601.87
        },
        {
            "date": "2024-12-11T06:58:00",
            "price": 601.51
        },
        {
            "date": "2024-12-11T10:06:00",
            "price": 601.19
        },
        {
            "date": "2024-12-11T13:16:00",
            "price": 600.85
        },
        {
            "date": "2024-12-11T17:22:00",
            "price": 600.41
        },
        {
            "date": "2024-12-12T00:36:00",
            "price": 599.53
        },
        {
            "date": "2024-12-12T05:04:00",
            "price": 599.26
        },
        {
            "date": "2024-12-12T22:18:00",
            "price": 584.44
        },
        {
            "date": "2024-12-13T00:40:00",
            "price": 573.99
        },
        {
            "date": "2024-12-13T04:32:00",
            "price": 564.07
        },
        {
            "date": "2024-12-13T08:38:00",
            "price": 563.62
        },
        {
            "date": "2024-12-13T15:52:00",
            "price": 559.66
        },
        {
            "date": "2024-12-13T21:20:00",
            "price": 525.0
        },
        {
            "date": "2024-12-13T23:10:00",
            "price": 524.95
        },
        {
            "date": "2024-12-14T17:40:00",
            "price": 509.95
        },
        {
            "date": "2024-12-14T20:44:00",
            "price": 509.9
        },
        {
            "date": "2024-12-16T19:24:00",
            "price": 578.94
        },
        {
            "date": "2024-12-17T00:18:00",
            "price": 569.64
        },
        {
            "date": "2024-12-17T05:28:00",
            "price": 547.09
        },
        {
            "date": "2024-12-17T06:52:00",
            "price": 544.11
        },
        {
            "date": "2024-12-20T01:34:00",
            "price": 544.02
        },
        {
            "date": "2024-12-23T23:22:00",
            "price": 543.75
        },
        {
            "date": "2024-12-24T00:36:00",
            "price": 543.7
        },
        {
            "date": "2024-12-24T12:54:00",
            "price": 543.44
        },
        {
            "date": "2024-12-24T19:18:00",
            "price": 543.19
        },
        {
            "date": "2024-12-24T23:14:00",
            "price": 543.09
        },
        {
            "date": "2024-12-25T14:00:00",
            "price": 542.84
        },
        {
            "date": "2024-12-26T04:52:00",
            "price": 542.79
        },
        {
            "date": "2024-12-26T12:58:00",
            "price": 542.74
        },
        {
            "date": "2024-12-27T00:46:00",
            "price": 579.99
        },
        {
            "date": "2024-12-31T03:54:00",
            "price": 578.99
        },
        {
            "date": "2024-12-31T09:48:00",
            "price": 579.99
        },
        {
            "date": "2025-01-01T01:36:00",
            "price": 579.94
        },
        {
            "date": "2025-01-02T17:54:00",
            "price": 579.89
        },
        {
            "date": "2025-01-03T05:08:00",
            "price": 578.99
        },
        {
            "date": "2025-01-03T10:04:00",
            "price": 578.94
        },
        {
            "date": "2025-01-05T11:16:00",
            "price": 579.89
        },
        {
            "date": "2025-01-05T17:26:00",
            "price": 578.94
        },
        {
            "date": "2025-01-06T20:10:00",
            "price": 579.89
        },
        {
            "date": "2025-01-07T06:14:00",
            "price": 519.87
        },
        {
            "date": "2025-01-07T09:36:00",
            "price": 519.33
        },
        {
            "date": "2025-01-07T23:44:00",
            "price": 519.94
        },
        {
            "date": "2025-01-08T01:04:00",
            "price": 519.76
        },
        {
            "date": "2025-01-08T02:14:00",
            "price": 519.93
        },
        {
            "date": "2025-01-08T07:12:00",
            "price": 519.34
        },
        {
            "date": "2025-01-08T09:44:00",
            "price": 518.92
        },
        {
            "date": "2025-01-08T14:48:00",
            "price": 518.19
        },
        {
            "date": "2025-01-09T00:02:00",
            "price": 516.69
        },
        {
            "date": "2025-01-09T05:28:00",
            "price": 515.8
        },
        {
            "date": "2025-01-09T06:32:00",
            "price": 519.87
        },
        {
            "date": "2025-01-09T22:46:00",
            "price": 519.52
        },
        {
            "date": "2025-01-10T02:46:00",
            "price": 518.91
        },
        {
            "date": "2025-01-10T10:00:00",
            "price": 519.52
        },
        {
            "date": "2025-01-10T14:38:00",
            "price": 519.93
        },
        {
            "date": "2025-01-10T17:46:00",
            "price": 519.46
        },
        {
            "date": "2025-01-10T20:54:00",
            "price": 519.64
        },
        {
            "date": "2025-01-11T00:02:00",
            "price": 519.16
        },
        {
            "date": "2025-01-11T03:10:00",
            "price": 518.97
        },
        {
            "date": "2025-01-11T05:08:00",
            "price": 519.93
        },
        {
            "date": "2025-01-11T08:40:00",
            "price": 519.34
        },
        {
            "date": "2025-01-11T12:10:00",
            "price": 519.64
        },
        {
            "date": "2025-01-11T18:22:00",
            "price": 519.57
        },
        {
            "date": "2025-01-12T01:36:00",
            "price": 518.43
        },
        {
            "date": "2025-01-12T09:52:00",
            "price": 519.28
        },
        {
            "date": "2025-01-12T12:00:00",
            "price": 518.97
        },
        {
            "date": "2025-01-12T16:04:00",
            "price": 519.46
        },
        {
            "date": "2025-01-13T00:20:00",
            "price": 518.13
        },
        {
            "date": "2025-01-13T04:50:00",
            "price": 517.41
        },
        {
            "date": "2025-01-13T07:26:00",
            "price": 519.64
        },
        {
            "date": "2025-01-13T08:40:00",
            "price": 519.82
        },
        {
            "date": "2025-01-13T13:46:00",
            "price": 519.33
        },
        {
            "date": "2025-01-13T21:20:00",
            "price": 519.58
        },
        {
            "date": "2025-01-14T02:44:00",
            "price": 518.86
        },
        {
            "date": "2025-01-14T06:02:00",
            "price": 518.26
        },
        {
            "date": "2025-01-14T09:10:00",
            "price": 517.78
        },
        {
            "date": "2025-01-14T14:06:00",
            "price": 516.94
        },
        {
            "date": "2025-01-14T15:24:00",
            "price": 516.75
        },
        {
            "date": "2025-01-14T20:18:00",
            "price": 514.4
        },
        {
            "date": "2025-01-15T03:32:00",
            "price": 516.88
        },
        {
            "date": "2025-01-15T05:08:00",
            "price": 510.53
        },
        {
            "date": "2025-01-15T07:28:00",
            "price": 508.65
        },
        {
            "date": "2025-01-15T08:42:00",
            "price": 506.87
        },
        {
            "date": "2025-01-15T11:50:00",
            "price": 499.81
        },
        {
            "date": "2025-01-15T15:48:00",
            "price": 499.22
        },
        {
            "date": "2025-01-15T21:52:00",
            "price": 513.07
        },
        {
            "date": "2025-01-16T00:24:00",
            "price": 499.94
        },
        {
            "date": "2025-01-16T04:40:00",
            "price": 499.83
        },
        {
            "date": "2025-01-16T17:44:00",
            "price": 494.63
        },
        {
            "date": "2025-01-17T00:14:00",
            "price": 489.95
        },
        {
            "date": "2025-01-17T23:22:00",
            "price": 499.63
        },
        {
            "date": "2025-01-18T03:32:00",
            "price": 498.97
        },
        {
            "date": "2025-01-18T13:52:00",
            "price": 499.63
        },
        {
            "date": "2025-01-18T16:50:00",
            "price": 502.15
        },
        {
            "date": "2025-01-18T19:58:00",
            "price": 499.69
        },
        {
            "date": "2025-01-18T21:52:00",
            "price": 499.39
        },
        {
            "date": "2025-01-19T01:00:00",
            "price": 498.86
        },
        {
            "date": "2025-01-19T04:20:00",
            "price": 498.32
        },
        {
            "date": "2025-01-19T08:24:00",
            "price": 497.66
        },
        {
            "date": "2025-01-19T11:36:00",
            "price": 499.81
        },
        {
            "date": "2025-01-19T18:48:00",
            "price": 502.28
        },
        {
            "date": "2025-01-20T05:08:00",
            "price": 509.73
        },
        {
            "date": "2025-01-21T11:12:00",
            "price": 509.37
        },
        {
            "date": "2025-01-21T22:16:00",
            "price": 512.36
        },
        {
            "date": "2025-01-23T21:32:00",
            "price": 506.47
        },
        {
            "date": "2025-01-24T04:56:00",
            "price": 505.25
        },
        {
            "date": "2025-01-26T08:40:00",
            "price": 504.76
        },
        {
            "date": "2025-01-26T12:36:00",
            "price": 519.58
        },
        {
            "date": "2025-01-26T20:58:00",
            "price": 518.37
        },
        {
            "date": "2025-01-26T21:40:00",
            "price": 519.93
        },
        {
            "date": "2025-01-27T00:48:00",
            "price": 519.64
        },
        {
            "date": "2025-01-27T03:56:00",
            "price": 519.88
        },
        {
            "date": "2025-01-27T07:16:00",
            "price": 519.39
        },
        {
            "date": "2025-01-27T12:20:00",
            "price": 671.52
        },
        {
            "date": "2025-01-27T15:44:00",
            "price": 670.93
        },
        {
            "date": "2025-01-27T17:24:00",
            "price": 670.69
        },
        {
            "date": "2025-01-27T20:16:00",
            "price": 497.49
        },
        {
            "date": "2025-01-28T00:04:00",
            "price": 496.12
        },
        {
            "date": "2025-01-28T02:36:00",
            "price": 495.81
        },
        {
            "date": "2025-01-28T06:02:00",
            "price": 671.59
        },
        {
            "date": "2025-01-28T09:12:00",
            "price": 671.41
        },
        {
            "date": "2025-01-28T15:16:00",
            "price": 670.69
        },
        {
            "date": "2025-01-28T20:32:00",
            "price": 670.15
        },
        {
            "date": "2025-01-28T22:56:00",
            "price": 669.91
        },
        {
            "date": "2025-01-29T01:16:00",
            "price": 669.6
        },
        {
            "date": "2025-01-29T02:08:00",
            "price": 669.42
        },
        {
            "date": "2025-01-29T05:08:00",
            "price": 668.95
        },
        {
            "date": "2025-01-29T08:32:00",
            "price": 668.41
        },
        {
            "date": "2025-01-29T18:14:00",
            "price": 671.34
        },
        {
            "date": "2025-01-29T20:14:00",
            "price": 497.8
        },
        {
            "date": "2025-01-30T06:12:00",
            "price": 671.59
        },
        {
            "date": "2025-01-30T08:48:00",
            "price": 671.16
        },
        {
            "date": "2025-01-30T11:56:00",
            "price": 671.76
        },
        {
            "date": "2025-01-30T14:28:00",
            "price": 671.77
        },
        {
            "date": "2025-01-30T22:26:00",
            "price": 670.1
        },
        {
            "date": "2025-01-31T13:56:00",
            "price": 484.95
        },
        {
            "date": "2025-02-01T01:26:00",
            "price": 480.06
        },
        {
            "date": "2025-02-01T04:40:00",
            "price": 479.68
        },
        {
            "date": "2025-02-01T08:16:00",
            "price": 479.2
        },
        {
            "date": "2025-02-01T11:20:00",
            "price": 478.68
        },
        {
            "date": "2025-02-01T14:36:00",
            "price": 478.14
        },
        {
            "date": "2025-02-01T21:08:00",
            "price": 477.06
        },
        {
            "date": "2025-02-02T03:56:00",
            "price": 475.85
        },
        {
            "date": "2025-02-02T06:40:00",
            "price": 475.28
        },
        {
            "date": "2025-02-02T08:48:00",
            "price": 474.83
        },
        {
            "date": "2025-02-02T10:00:00",
            "price": 474.65
        },
        {
            "date": "2025-02-02T13:40:00",
            "price": 473.98
        },
        {
            "date": "2025-02-02T21:18:00",
            "price": 472.54
        },
        {
            "date": "2025-02-03T03:58:00",
            "price": 471.91
        },
        {
            "date": "2025-02-08T13:02:00",
            "price": 529.99
        },
        {
            "date": "2025-02-09T16:48:00",
            "price": 471.91
        },
        {
            "date": "2025-02-11T02:36:00",
            "price": 499.99
        },
        {
            "date": "2025-02-13T22:50:00",
            "price": 499.99
        },
        {
            "date": "2025-02-19T06:04:00",
            "price": 558.56
        },
        {
            "date": "2025-02-19T10:48:00",
            "price": 558.02
        },
        {
            "date": "2025-02-19T14:02:00",
            "price": 557.6
        },
        {
            "date": "2025-02-19T17:10:00",
            "price": 557.22
        },
        {
            "date": "2025-02-19T22:26:00",
            "price": 556.64
        },
        {
            "date": "2025-02-20T01:34:00",
            "price": 556.24
        },
        {
            "date": "2025-02-20T04:42:00",
            "price": 555.88
        },
        {
            "date": "2025-02-20T07:34:00",
            "price": 555.58
        },
        {
            "date": "2025-02-20T08:52:00",
            "price": 555.4
        },
        {
            "date": "2025-02-20T12:40:00",
            "price": 554.96
        },
        {
            "date": "2025-02-21T21:00:00",
            "price": 536.22
        },
        {
            "date": "2025-02-22T05:40:00",
            "price": 495.43
        },
        {
            "date": "2025-02-22T10:56:00",
            "price": 494.86
        },
        {
            "date": "2025-02-22T20:08:00",
            "price": 494.88
        },
        {
            "date": "2025-02-26T03:00:00",
            "price": 505.3
        },
        {
            "date": "2025-02-26T18:00:00",
            "price": 510.0
        },
        {
            "date": "2025-02-26T22:10:00",
            "price": 504.99
        },
        {
            "date": "2025-02-27T01:48:00",
            "price": 505.96
        },
        {
            "date": "2025-02-27T06:56:00",
            "price": 508.0
        },
        {
            "date": "2025-02-27T19:10:00",
            "price": 505.25
        },
        {
            "date": "2025-02-27T23:28:00",
            "price": 504.2
        },
        {
            "date": "2025-02-28T23:46:00",
            "price": 504.8
        },
        {
            "date": "2025-03-01T06:00:00",
            "price": 509.5
        },
        {
            "date": "2025-03-02T19:10:00",
            "price": 510.0
        },
        {
            "date": "2025-03-07T01:28:00",
            "price": 499.99
        },
        {
            "date": "2025-03-07T23:26:00",
            "price": 499.94
        },
        {
            "date": "2025-03-08T02:34:00",
            "price": 499.99
        },
        {
            "date": "2025-03-08T05:42:00",
            "price": 499.94
        },
        {
            "date": "2025-03-08T08:50:00",
            "price": 510.0
        },
        {
            "date": "2025-03-08T16:58:00",
            "price": 499.94
        },
        {
            "date": "2025-03-09T14:04:00",
            "price": 510.0
        },
        {
            "date": "2025-03-13T18:22:00",
            "price": 551.62
        },
        {
            "date": "2025-03-13T23:48:00",
            "price": 563.44
        },
        {
            "date": "2025-03-14T00:00:00",
            "price": 563.42
        },
        {
            "date": "2025-03-14T03:56:00",
            "price": 562.94
        },
        {
            "date": "2025-03-14T06:58:00",
            "price": 562.6
        },
        {
            "date": "2025-03-14T10:06:00",
            "price": 562.22
        },
        {
            "date": "2025-03-14T14:16:00",
            "price": 561.68
        },
        {
            "date": "2025-03-14T22:32:00",
            "price": 576.2
        },
        {
            "date": "2025-03-15T04:20:00",
            "price": 561.49
        },
        {
            "date": "2025-03-17T04:22:00",
            "price": 575.2
        },
        {
            "date": "2025-03-17T15:20:00",
            "price": 574.2
        },
        {
            "date": "2025-03-17T21:32:00",
            "price": 569.57
        },
        {
            "date": "2025-03-18T12:40:00",
            "price": 562.5
        },
        {
            "date": "2025-03-18T19:48:00",
            "price": 557.34
        },
        {
            "date": "2025-03-19T04:48:00",
            "price": 556.56
        },
        {
            "date": "2025-03-19T12:10:00",
            "price": 555.12
        },
        {
            "date": "2025-03-19T15:18:00",
            "price": 554.46
        },
        {
            "date": "2025-03-19T21:18:00",
            "price": 553.31
        },
        {
            "date": "2025-03-20T00:28:00",
            "price": 552.74
        },
        {
            "date": "2025-03-20T02:10:00",
            "price": 556.95
        },
        {
            "date": "2025-03-20T07:40:00",
            "price": 552.26
        },
        {
            "date": "2025-03-20T14:54:00",
            "price": 557.03
        },
        {
            "date": "2025-03-20T16:02:00",
            "price": 562.14
        },
        {
            "date": "2025-03-20T20:14:00",
            "price": 561.04
        },
        {
            "date": "2025-03-20T23:28:00",
            "price": 560.04
        },
        {
            "date": "2025-03-21T09:48:00",
            "price": 558.1
        },
        {
            "date": "2025-03-21T15:58:00",
            "price": 557.06
        },
        {
            "date": "2025-03-21T20:24:00",
            "price": 556.06
        },
        {
            "date": "2025-03-22T03:12:00",
            "price": 555.06
        },
        {
            "date": "2025-03-22T17:02:00",
            "price": 554.68
        },
        {
            "date": "2025-03-22T18:46:00",
            "price": 554.46
        },
        {
            "date": "2025-03-22T21:54:00",
            "price": 554.04
        },
        {
            "date": "2025-03-23T01:02:00",
            "price": 553.72
        },
        {
            "date": "2025-03-23T04:10:00",
            "price": 553.34
        },
        {
            "date": "2025-03-23T05:16:00",
            "price": 553.24
        },
        {
            "date": "2025-03-23T11:40:00",
            "price": 552.52
        },
        {
            "date": "2025-03-23T19:52:00",
            "price": 551.5
        },
        {
            "date": "2025-03-23T23:00:00",
            "price": 551.08
        },
        {
            "date": "2025-03-24T02:08:00",
            "price": 550.7
        },
        {
            "date": "2025-03-24T05:08:00",
            "price": 550.38
        },
        {
            "date": "2025-03-24T08:16:00",
            "price": 549.98
        },
        {
            "date": "2025-03-24T12:06:00",
            "price": 549.56
        },
        {
            "date": "2025-03-24T16:20:00",
            "price": 549.1
        },
        {
            "date": "2025-03-24T19:36:00",
            "price": 554.51
        },
        {
            "date": "2025-03-25T04:00:00",
            "price": 553.51
        },
        {
            "date": "2025-03-25T16:44:00",
            "price": 555.56
        },
        {
            "date": "2025-03-25T19:54:00",
            "price": 554.51
        },
        {
            "date": "2025-03-25T23:02:00",
            "price": 553.46
        },
        {
            "date": "2025-03-26T05:18:00",
            "price": 550.29
        },
        {
            "date": "2025-03-26T19:04:00",
            "price": 550.3
        },
        {
            "date": "2025-03-26T23:56:00",
            "price": 550.28
        },
        {
            "date": "2025-03-27T05:00:00",
            "price": 551.39
        },
        {
            "date": "2025-03-27T08:12:00",
            "price": 551.27
        },
        {
            "date": "2025-03-27T17:30:00",
            "price": 550.31
        },
        {
            "date": "2025-03-27T19:52:00",
            "price": 550.05
        },
        {
            "date": "2025-03-27T23:22:00",
            "price": 549.69
        },
        {
            "date": "2025-03-28T00:00:00",
            "price": 549.65
        },
        {
            "date": "2025-03-28T03:20:00",
            "price": 549.21
        },
        {
            "date": "2025-03-28T04:56:00",
            "price": 549.07
        },
        {
            "date": "2025-03-28T09:32:00",
            "price": 548.63
        },
        {
            "date": "2025-03-28T11:20:00",
            "price": 548.49
        },
        {
            "date": "2025-03-28T15:28:00",
            "price": 548.25
        },
        {
            "date": "2025-03-29T00:34:00",
            "price": 538.91
        },
        {
            "date": "2025-03-29T03:42:00",
            "price": 538.67
        },
        {
            "date": "2025-03-29T05:04:00",
            "price": 538.61
        },
        {
            "date": "2025-03-29T08:04:00",
            "price": 538.37
        },
        {
            "date": "2025-03-29T13:20:00",
            "price": 537.81
        },
        {
            "date": "2025-03-29T19:44:00",
            "price": 537.31
        },
        {
            "date": "2025-03-29T22:58:00",
            "price": 536.97
        },
        {
            "date": "2025-03-30T04:54:00",
            "price": 536.31
        },
        {
            "date": "2025-03-30T09:24:00",
            "price": 535.83
        },
        {
            "date": "2025-03-30T11:20:00",
            "price": 535.61
        },
        {
            "date": "2025-03-30T18:40:00",
            "price": 534.89
        },
        {
            "date": "2025-03-30T21:48:00",
            "price": 534.55
        },
        {
            "date": "2025-03-31T02:00:00",
            "price": 534.15
        },
        {
            "date": "2025-03-31T04:50:00",
            "price": 533.89
        },
        {
            "date": "2025-03-31T07:58:00",
            "price": 533.55
        },
        {
            "date": "2025-03-31T09:44:00",
            "price": 533.41
        },
        {
            "date": "2025-03-31T14:24:00",
            "price": 532.95
        },
        {
            "date": "2025-03-31T18:24:00",
            "price": 532.55
        },
        {
            "date": "2025-03-31T22:40:00",
            "price": 532.03
        },
        {
            "date": "2025-04-01T00:34:00",
            "price": 531.79
        },
        {
            "date": "2025-04-01T05:16:00",
            "price": 531.21
        },
        {
            "date": "2025-04-01T10:06:00",
            "price": 530.63
        },
        {
            "date": "2025-04-01T11:20:00",
            "price": 530.45
        },
        {
            "date": "2025-04-01T22:26:00",
            "price": 521.72
        },
        {
            "date": "2025-04-02T03:52:00",
            "price": 504.99
        },
        {
            "date": "2025-04-02T16:04:00",
            "price": 510.17
        },
        {
            "date": "2025-04-02T18:40:00",
            "price": 509.97
        },
        {
            "date": "2025-04-02T23:16:00",
            "price": 513.64
        },
        {
            "date": "2025-04-03T08:00:00",
            "price": 514.78
        },
        {
            "date": "2025-04-03T20:36:00",
            "price": 514.73
        },
        {
            "date": "2025-04-04T06:24:00",
            "price": 528.55
        },
        {
            "date": "2025-04-05T04:08:00",
            "price": 499.95
        },
        {
            "date": "2025-04-05T19:30:00",
            "price": 457.95
        },
        {
            "date": "2025-04-07T16:28:00",
            "price": 528.13
        },
        {
            "date": "2025-04-07T19:20:00",
            "price": 528.0
        },
        {
            "date": "2025-04-08T01:12:00",
            "price": 527.74
        },
        {
            "date": "2025-04-08T05:32:00",
            "price": 527.22
        },
        {
            "date": "2025-04-08T10:32:00",
            "price": 526.6
        },
        {
            "date": "2025-04-08T17:26:00",
            "price": 525.87
        },
        {
            "date": "2025-04-08T20:34:00",
            "price": 525.53
        },
        {
            "date": "2025-04-08T23:56:00",
            "price": 525.08
        },
        {
            "date": "2025-04-09T04:12:00",
            "price": 524.62
        }
    ],
    "asin": "B0CK5T84WJ"
}